[
  {
    "damage": [
      12,
      12
    ],
    "framesOnBlock": {
      "_raw": "+1",
      "lower": "+1",
      "properties": []
    },
    "framesOnCounter": {
      "_raw": "",
      "lower": "",
      "properties": []
    },
    "framesOnHit": {
      "_raw": "+2c",
      "lower": "+2",
      "properties": [
        "c"
      ]
    },
    "framesOnStartup": {
      "_raw": "i16",
      "lower": "i16",
      "properties": []
    },
    "hitLevels": [
      "m"
    ],
    "index": 0,
    "input": "2+3",
    "name": "Heat Burst",
    "notes": [
      "Cancel to r45 with b,b",
      "3 chip damage on block",
      "12 chip damage on hit",
      "Only deals recoverable damage",
      "Cannot cause a K.O."
    ],
    "specials": [
      "Heat Burst"
    ],
    "state": {
      "_raw": ""
    }
  },
  {
    "damage": [
      57
    ],
    "framesOnBlock": {
      "_raw": "+3",
      "lower": "+3",
      "properties": []
    },
    "framesOnCounter": {
      "_raw": "",
      "lower": "",
      "properties": []
    },
    "framesOnHit": {
      "_raw": "+0d",
      "lower": "+0",
      "properties": [
        "d"
      ]
    },
    "framesOnStartup": {
      "_raw": "i15~16",
      "lower": "i15",
      "properties": [],
      "upper": "16"
    },
    "hitLevels": [
      "m",
      "h",
      "m"
    ],
    "index": 1,
    "input": "H.2+3",
    "name": "Hellfire Trespass Slayer",
    "notes": [
      "Transition to attack throw after 1st hit",
      "Transitions to Breaking Step automatically on block",
      "Cancel Breaking Step transition with B",
      "Chip damage on block",
      "Jail from 1st attack",
      "Ends Heat"
    ],
    "specials": [
      "Heat Smash",
      "Reversal Break",
      "Balcony Break"
    ],
    "state": {
      "_raw": ""
    }
  },
  {
    "damage": [
      48
    ],
    "framesOnBlock": {
      "_raw": "+9",
      "lower": "+9",
      "properties": []
    },
    "framesOnCounter": {
      "_raw": "",
      "lower": "",
      "properties": []
    },
    "framesOnHit": {
      "_raw": "+32a (-4)",
      "lower": "+32",
      "properties": [
        "a"
      ],
      "tech": "-4"
    },
    "framesOnStartup": {
      "_raw": "i15~16",
      "lower": "i15",
      "properties": [],
      "upper": "16"
    },
    "hitLevels": [
      "m",
      "h",
      "m"
    ],
    "index": 2,
    "input": "H.2+3,4",
    "name": "Hellfire Darkside Slayer",
    "notes": [
      "Chip damage on block",
      "Jail from 1st attack",
      "Ends Heat"
    ],
    "specials": [
      "Heat Smash",
      "Wall Crush +21g on block",
      "Reversal Break",
      "Balcony Break"
    ],
    "state": {
      "_raw": ""
    }
  },
  {
    "damage": [
      4,
      4,
      16
    ],
    "framesOnBlock": {
      "_raw": "-14",
      "lower": "-14",
      "properties": []
    },
    "framesOnCounter": {
      "_raw": "",
      "lower": "",
      "properties": []
    },
    "framesOnHit": {
      "_raw": "+12a (+3)",
      "lower": "+12",
      "properties": [
        "a"
      ],
      "tech": "+3"
    },
    "framesOnStartup": {
      "_raw": "i13 i8 i12",
      "lower": "i13",
      "properties": []
    },
    "hitLevels": [
      "m",
      "m",
      "h"
    ],
    "index": 3,
    "input": "1+2",
    "name": "Median Line Destruction",
    "notes": [],
    "specials": [
      "Balcony Break",
      "Heat Engager",
      "Heat Dash +43a (+35), +5"
    ],
    "state": {
      "_raw": ""
    }
  },
  {
    "damage": [
      12,
      17
    ],
    "framesOnBlock": {
      "_raw": "-12",
      "lower": "-12",
      "properties": []
    },
    "framesOnCounter": {
      "_raw": "",
      "lower": "",
      "properties": []
    },
    "framesOnHit": {
      "_raw": "+4",
      "lower": "+4",
      "properties": []
    },
    "framesOnStartup": {
      "_raw": ",i22",
      "lower": "i22",
      "properties": []
    },
    "hitLevels": [
      "m",
      "m"
    ],
    "index": 4,
    "input": "f+3,1",
    "name": "Tanden Nidan-uchi",
    "notes": [
      "Combo from 1st hit",
      "Balcony break on airborne hit"
    ],
    "specials": [
      "Heat Engager",
      "Heat Dash +36a (+26), +5"
    ],
    "state": {
      "_raw": ""
    }
  },
  {
    "damage": [
      22
    ],
    "framesOnBlock": {
      "_raw": "+0",
      "lower": "+0",
      "properties": []
    },
    "framesOnCounter": {
      "_raw": "",
      "lower": "",
      "properties": []
    },
    "framesOnHit": {
      "_raw": "+8c",
      "lower": "+8",
      "properties": [
        "c"
      ]
    },
    "framesOnStartup": {
      "_raw": "i20~i21",
      "lower": "i20",
      "properties": [],
      "upper": "i21"
    },
    "hitLevels": [
      "m"
    ],
    "index": 5,
    "input": "df+4",
    "name": "Right Spinning Axe Kick",
    "notes": [],
    "specials": [
      "Spike",
      "Heat Engager",
      "Heat Dash +67a (+50), +5"
    ],
    "state": {
      "_raw": ""
    }
  },
  {
    "damage": [
      22
    ],
    "framesOnBlock": {
      "_raw": "-8",
      "lower": "-8",
      "properties": []
    },
    "framesOnCounter": {
      "_raw": "",
      "lower": "",
      "properties": []
    },
    "framesOnHit": {
      "_raw": "+15a (+6)",
      "lower": "+15",
      "properties": [
        "a"
      ],
      "tech": "+6"
    },
    "framesOnStartup": {
      "_raw": "i14~15",
      "lower": "i14",
      "properties": [],
      "upper": "15"
    },
    "hitLevels": [
      "m"
    ],
    "index": 6,
    "input": "f,F+2",
    "name": "Demon's Paw",
    "notes": [
      "Cannot be buffered",
      "6 chip damage on block"
    ],
    "specials": [
      "Heat Engager",
      "Heat Dash +36a (+26), +5",
      "Balcony Break"
    ],
    "state": {
      "_raw": ""
    }
  },
  {
    "damage": [
      27
    ],
    "framesOnBlock": {
      "_raw": "-5",
      "lower": "-5",
      "properties": []
    },
    "framesOnCounter": {
      "_raw": "",
      "lower": "",
      "properties": []
    },
    "framesOnHit": {
      "_raw": "+17a (+8)",
      "lower": "+17",
      "properties": [
        "a"
      ],
      "tech": "+8"
    },
    "framesOnStartup": {
      "_raw": "i21~i22",
      "lower": "i21",
      "properties": [],
      "upper": "i22"
    },
    "hitLevels": [
      "h"
    ],
    "index": 7,
    "input": "ZEN.2",
    "name": "Fiendish Claw",
    "notes": [
      "Chip damage on block",
      "+0 on block after absorbing an attack"
    ],
    "specials": [
      "Heat Engager",
      "Heat Dash +34a (+27), +5",
      "Homing",
      "Balcony Break"
    ],
    "state": {
      "_raw": ""
    }
  },
  {
    "damage": [
      0
    ],
    "framesOnBlock": {
      "_raw": "+4",
      "lower": "+4",
      "properties": []
    },
    "framesOnCounter": {
      "_raw": "",
      "lower": "",
      "properties": []
    },
    "framesOnHit": {
      "_raw": "+23g~+38g",
      "lower": "+23",
      "properties": [
        "g",
        "g"
      ],
      "upper": "+38"
    },
    "framesOnStartup": {
      "_raw": "i19~34",
      "lower": "i19",
      "properties": [],
      "upper": "34"
    },
    "hitLevels": [
      "M"
    ],
    "index": 8,
    "input": "H.db+1+2",
    "name": "Awakened Power Stance",
    "notes": [
      "Enter Awakened Breaking Step r10 on hit or block",
      "Unparryable by traditional parries, Asuka, Nina, etc",
      "Partially uses remaining Heat time",
      "Causes wall splat on hit",
      "Opponent recovers crouching"
    ],
    "specials": [
      "Strong Aerial Tailspin",
      "Balcony Break"
    ],
    "state": {
      "_raw": ""
    }
  },
  {
    "damage": [
      0,
      25
    ],
    "framesOnBlock": {
      "_raw": "-13",
      "lower": "-13",
      "properties": []
    },
    "framesOnCounter": {
      "_raw": "",
      "lower": "",
      "properties": []
    },
    "framesOnHit": {
      "_raw": "+72a (+56)",
      "lower": "+72",
      "properties": [
        "a"
      ],
      "tech": "+56"
    },
    "framesOnStartup": {
      "_raw": ",i20~22",
      "lower": "i20",
      "properties": [],
      "upper": "22"
    },
    "hitLevels": [
      "M",
      "m"
    ],
    "index": 9,
    "input": "H.db+1+2,1",
    "name": "Awakened Thunder God Fist",
    "notes": [
      "10 chip damage on block"
    ],
    "specials": [
      "Tornado"
    ],
    "state": {
      "_raw": ""
    }
  },
  {
    "damage": [
      0,
      23
    ],
    "framesOnBlock": {
      "_raw": "+4",
      "lower": "+4",
      "properties": []
    },
    "framesOnCounter": {
      "_raw": "",
      "lower": "",
      "properties": []
    },
    "framesOnHit": {
      "_raw": "+38a (+28)",
      "lower": "+38",
      "properties": [
        "a"
      ],
      "tech": "+28"
    },
    "framesOnStartup": {
      "_raw": ",i11~12",
      "lower": "i11",
      "properties": [],
      "upper": "12"
    },
    "hitLevels": [
      "M",
      "sm"
    ],
    "index": 10,
    "input": "H.db+1+2,2",
    "name": "Awakened Wind God Fist",
    "notes": [
      "9 chip damage on block"
    ],
    "specials": [],
    "state": {
      "_raw": ""
    }
  },
  {
    "damage": [
      0,
      25
    ],
    "framesOnBlock": {
      "_raw": "+2c",
      "lower": "+2",
      "properties": [
        "c"
      ]
    },
    "framesOnCounter": {
      "_raw": "",
      "lower": "",
      "properties": []
    },
    "framesOnHit": {
      "_raw": "+22a",
      "lower": "+22",
      "properties": [
        "a"
      ]
    },
    "framesOnStartup": {
      "_raw": ",i26~28",
      "lower": "i26",
      "properties": [],
      "upper": "28"
    },
    "hitLevels": [
      "M",
      "M"
    ],
    "index": 11,
    "input": "H.db+1+2,3",
    "name": "Awakened Demon's Hoof",
    "notes": [
      "10 chip damage on block"
    ],
    "specials": [
      "Spike"
    ],
    "state": {
      "_raw": ""
    }
  },
  {
    "damage": [
      0,
      24
    ],
    "framesOnBlock": {
      "_raw": "-23",
      "lower": "-23",
      "properties": []
    },
    "framesOnCounter": {
      "_raw": "",
      "lower": "",
      "properties": []
    },
    "framesOnHit": {
      "_raw": "-2a",
      "lower": "-2",
      "properties": [
        "a"
      ]
    },
    "framesOnStartup": {
      "_raw": ",i33~34",
      "lower": "i33",
      "properties": [],
      "upper": "34"
    },
    "hitLevels": [
      "M",
      "L"
    ],
    "index": 12,
    "input": "H.db+1+2,DF+3",
    "name": "Awakened Demon's Tail",
    "notes": [
      "10 chip damage on block"
    ],
    "specials": [],
    "state": {
      "_raw": ""
    }
  },
  {
    "damage": [
      0,
      10
    ],
    "framesOnBlock": {
      "_raw": "-23",
      "lower": "-23",
      "properties": []
    },
    "framesOnCounter": {
      "_raw": "",
      "lower": "",
      "properties": []
    },
    "framesOnHit": {
      "_raw": "+22a",
      "lower": "+22",
      "properties": [
        "a"
      ]
    },
    "framesOnStartup": {
      "_raw": ",i16",
      "lower": "i16",
      "properties": []
    },
    "hitLevels": [
      "M",
      "L"
    ],
    "index": 13,
    "input": "H.db+1+2,4",
    "name": "",
    "notes": [
      "4 chip damage on block"
    ],
    "specials": [],
    "state": {
      "_raw": ""
    }
  },
  {
    "damage": [
      0,
      10,
      28
    ],
    "framesOnBlock": {
      "_raw": "-23",
      "lower": "-23",
      "properties": []
    },
    "framesOnCounter": {
      "_raw": "",
      "lower": "",
      "properties": []
    },
    "framesOnHit": {
      "_raw": "+20d (-15)",
      "lower": "+20",
      "properties": [
        "d"
      ],
      "tech": "-15"
    },
    "framesOnStartup": {
      "_raw": ",i25~26",
      "lower": "i25",
      "properties": [],
      "upper": "26"
    },
    "hitLevels": [
      "M",
      "L",
      "m"
    ],
    "index": 14,
    "input": "H.db+1+2,4,4",
    "name": "Awakened Spinning Demon",
    "notes": [],
    "specials": [
      "Spike"
    ],
    "state": {
      "_raw": ""
    }
  },
  {
    "damage": [
      5
    ],
    "framesOnBlock": {
      "_raw": "+1",
      "lower": "+1",
      "properties": []
    },
    "framesOnCounter": {
      "_raw": "",
      "lower": "",
      "properties": []
    },
    "framesOnHit": {
      "_raw": "+8",
      "lower": "+8",
      "properties": []
    },
    "framesOnStartup": {
      "_raw": "i10",
      "lower": "i10",
      "properties": []
    },
    "hitLevels": [
      "h"
    ],
    "index": 15,
    "input": "1",
    "name": "Jab",
    "notes": [],
    "specials": [],
    "state": {
      "_raw": ""
    }
  },
  {
    "damage": [
      5,
      12
    ],
    "framesOnBlock": {
      "_raw": "-3",
      "lower": "-3",
      "properties": []
    },
    "framesOnCounter": {
      "_raw": "",
      "lower": "",
      "properties": []
    },
    "framesOnHit": {
      "_raw": "+6",
      "lower": "+6",
      "properties": []
    },
    "framesOnStartup": {
      "_raw": ",i10",
      "lower": "i10",
      "properties": []
    },
    "hitLevels": [
      "h",
      "h"
    ],
    "index": 16,
    "input": "1,2",
    "name": "Left Right Combo",
    "notes": [],
    "specials": [],
    "state": {
      "_raw": ""
    }
  },
  {
    "damage": [
      5,
      12,
      20
    ],
    "framesOnBlock": {
      "_raw": "-16",
      "lower": "-16",
      "properties": []
    },
    "framesOnCounter": {
      "_raw": "",
      "lower": "",
      "properties": []
    },
    "framesOnHit": {
      "_raw": "+31a (+21)",
      "lower": "+31",
      "properties": [
        "a"
      ],
      "tech": "+21"
    },
    "framesOnStartup": {
      "_raw": ",i20~22",
      "lower": "i20",
      "properties": [],
      "upper": "22"
    },
    "hitLevels": [
      "h",
      "h",
      "m"
    ],
    "index": 17,
    "input": "1,2,1",
    "name": "Left Right > Black Wing Rondo",
    "notes": [
      "Combo from 2nd CH with 7f delay",
      "Input can be delayed 9f",
      "Move can be delayed 4f",
      "Chip damage on block"
    ],
    "specials": [
      "Tornado"
    ],
    "state": {
      "_raw": ""
    }
  },
  {
    "damage": [
      5,
      12,
      20
    ],
    "framesOnBlock": {
      "_raw": "+0",
      "lower": "+0",
      "properties": []
    },
    "framesOnCounter": {
      "_raw": "",
      "lower": "",
      "properties": []
    },
    "framesOnHit": {
      "_raw": "+31d",
      "lower": "+31",
      "properties": [
        "d"
      ]
    },
    "framesOnStartup": {
      "_raw": ",i24~26",
      "lower": "i24",
      "properties": [],
      "upper": "26"
    },
    "hitLevels": [
      "h",
      "h",
      "m"
    ],
    "index": 18,
    "input": "1,2,3",
    "name": "Left Right > Axe Kick",
    "notes": [
      "Interrupt with i10 from 2nd block",
      "Input can be delayed 9f",
      "Move can be delayed 4f"
    ],
    "specials": [
      "Spike"
    ],
    "state": {
      "_raw": ""
    }
  },
  {
    "damage": [
      5,
      12,
      26
    ],
    "framesOnBlock": {
      "_raw": "-4",
      "lower": "-4",
      "properties": []
    },
    "framesOnCounter": {
      "_raw": "",
      "lower": "",
      "properties": []
    },
    "framesOnHit": {
      "_raw": "+23a (+14)",
      "lower": "+23",
      "properties": [
        "a"
      ],
      "tech": "+14"
    },
    "framesOnStartup": {
      "_raw": ",i20~22",
      "lower": "i20",
      "properties": [],
      "upper": "22"
    },
    "hitLevels": [
      "h",
      "h",
      "h"
    ],
    "index": 19,
    "input": "1,2,4",
    "name": "Left Right > Spinning Hook Kick",
    "notes": [
      "Combo from 3rd hit with 7f delay",
      "Input can be delayed 9f",
      "Move can be delayed 4f"
    ],
    "specials": [
      "Balcony Break"
    ],
    "state": {
      "_raw": ""
    }
  },
  {
    "damage": [
      5,
      9
    ],
    "framesOnBlock": {
      "_raw": "-12",
      "lower": "-12",
      "properties": []
    },
    "framesOnCounter": {
      "_raw": "",
      "lower": "",
      "properties": []
    },
    "framesOnHit": {
      "_raw": "-1",
      "lower": "-1",
      "properties": []
    },
    "framesOnStartup": {
      "_raw": ",i16~17",
      "lower": "i16",
      "properties": [],
      "upper": "17"
    },
    "hitLevels": [
      "h",
      "L"
    ],
    "index": 20,
    "input": "1,3",
    "name": "Left Jab > Single Low",
    "notes": [
      "Combo from 1st hit with 4f delay",
      "Grounded hit can be inconsistent"
    ],
    "specials": [],
    "state": {
      "_raw": ""
    }
  },
  {
    "damage": [
      5,
      9,
      17
    ],
    "framesOnBlock": {
      "_raw": "-13",
      "lower": "-13",
      "properties": []
    },
    "framesOnCounter": {
      "_raw": "+29a",
      "lower": "+29",
      "properties": [
        "a"
      ]
    },
    "framesOnHit": {
      "_raw": "+3",
      "lower": "+3",
      "properties": []
    },
    "framesOnStartup": {
      "_raw": ",i23",
      "lower": "i23",
      "properties": []
    },
    "hitLevels": [
      "h",
      "L",
      "l"
    ],
    "index": 21,
    "input": "1,3,4",
    "name": "Left Jab > Double Low",
    "notes": [
      "Combo from 2nd CH with 7f delay",
      "Input can be delayed 12f"
    ],
    "specials": [],
    "state": {
      "_raw": ""
    }
  },
  {
    "damage": [
      9
    ],
    "framesOnBlock": {
      "_raw": "+0",
      "lower": "+0",
      "properties": []
    },
    "framesOnCounter": {
      "_raw": "",
      "lower": "",
      "properties": []
    },
    "framesOnHit": {
      "_raw": "+9",
      "lower": "+9",
      "properties": []
    },
    "framesOnStartup": {
      "_raw": "i10",
      "lower": "i10",
      "properties": []
    },
    "hitLevels": [
      "h"
    ],
    "index": 22,
    "input": "2",
    "name": "Right Jab",
    "notes": [],
    "specials": [],
    "state": {
      "_raw": ""
    }
  },
  {
    "damage": [
      9,
      9
    ],
    "framesOnBlock": {
      "_raw": "-3",
      "lower": "-3",
      "properties": []
    },
    "framesOnCounter": {
      "_raw": "",
      "lower": "",
      "properties": []
    },
    "framesOnHit": {
      "_raw": "+6",
      "lower": "+6",
      "properties": []
    },
    "framesOnStartup": {
      "_raw": ",i16~17",
      "lower": "i16",
      "properties": [],
      "upper": "17"
    },
    "hitLevels": [
      "h",
      "m"
    ],
    "index": 23,
    "input": "2,1",
    "name": "Double Thrust",
    "notes": [
      "Jail from 1st attack with 2f delay",
      "Same animation as df+1"
    ],
    "specials": [],
    "state": {
      "_raw": ""
    }
  },
  {
    "damage": [
      9,
      9,
      18
    ],
    "framesOnBlock": {
      "_raw": "-9",
      "lower": "-9",
      "properties": []
    },
    "framesOnCounter": {
      "_raw": "+27a",
      "lower": "+27",
      "properties": [
        "a"
      ]
    },
    "framesOnHit": {
      "_raw": "+4",
      "lower": "+4",
      "properties": []
    },
    "framesOnStartup": {
      "_raw": ",i18~20",
      "lower": "i18",
      "properties": [],
      "upper": "20"
    },
    "hitLevels": [
      "h",
      "m",
      "m"
    ],
    "index": 24,
    "input": "2,1,4",
    "name": "Double Thrust > Roundhouse",
    "notes": [
      "Combo from 2nd CH with 8f delay",
      "Input can be delayed 10f"
    ],
    "specials": [],
    "state": {
      "_raw": ""
    }
  },
  {
    "damage": [
      9,
      9,
      20
    ],
    "framesOnBlock": {
      "_raw": "-31",
      "lower": "-31",
      "properties": []
    },
    "framesOnCounter": {
      "_raw": "",
      "lower": "",
      "properties": []
    },
    "framesOnHit": {
      "_raw": "+16a",
      "lower": "+16",
      "properties": [
        "a"
      ]
    },
    "framesOnStartup": {
      "_raw": ",i20~21",
      "lower": "i20",
      "properties": [],
      "upper": "21"
    },
    "hitLevels": [
      "h",
      "m",
      "l"
    ],
    "index": 25,
    "input": "2,1,4~4",
    "name": "Double Thrust > Low Trick Kick",
    "notes": [],
    "specials": [],
    "state": {
      "_raw": ""
    }
  },
  {
    "damage": [
      9,
      20
    ],
    "framesOnBlock": {
      "_raw": "-9",
      "lower": "-9",
      "properties": []
    },
    "framesOnCounter": {
      "_raw": "",
      "lower": "",
      "properties": []
    },
    "framesOnHit": {
      "_raw": "+11",
      "lower": "+11",
      "properties": []
    },
    "framesOnStartup": {
      "_raw": ",i24~27",
      "lower": "i24",
      "properties": [],
      "upper": "27"
    },
    "hitLevels": [
      "h",
      "h"
    ],
    "index": 26,
    "input": "2,4",
    "name": "Switchblade",
    "notes": [
      "Combo from 1st hit with 2f delay",
      "Enter ZEN -6 +14 r26 with F"
    ],
    "specials": [
      "Balcony Break"
    ],
    "state": {
      "_raw": ""
    }
  },
  {
    "damage": [
      19
    ],
    "framesOnBlock": {
      "_raw": "-7",
      "lower": "-7",
      "properties": []
    },
    "framesOnCounter": {
      "_raw": "",
      "lower": "",
      "properties": []
    },
    "framesOnHit": {
      "_raw": "+4",
      "lower": "+4",
      "properties": []
    },
    "framesOnStartup": {
      "_raw": "i14",
      "lower": "i14",
      "properties": []
    },
    "hitLevels": [
      "h"
    ],
    "index": 27,
    "input": "3",
    "name": "",
    "notes": [],
    "specials": [],
    "state": {
      "_raw": ""
    }
  },
  {
    "damage": [
      19,
      7
    ],
    "framesOnBlock": {
      "_raw": "-1",
      "lower": "-1",
      "properties": []
    },
    "framesOnCounter": {
      "_raw": "",
      "lower": "",
      "properties": []
    },
    "framesOnHit": {
      "_raw": "+7",
      "lower": "+7",
      "properties": []
    },
    "framesOnStartup": {
      "_raw": ",i20",
      "lower": "i20",
      "properties": []
    },
    "hitLevels": [
      "h",
      "h"
    ],
    "index": 28,
    "input": "3,1",
    "name": "",
    "notes": [
      "Combo from 1st hit",
      "Enter ZEN +4 +12 r15 with F"
    ],
    "specials": [],
    "state": {
      "_raw": ""
    }
  },
  {
    "damage": [
      19,
      7,
      18
    ],
    "framesOnBlock": {
      "_raw": "-13",
      "lower": "-13",
      "properties": []
    },
    "framesOnCounter": {
      "_raw": "+29a",
      "lower": "+29",
      "properties": [
        "a"
      ]
    },
    "framesOnHit": {
      "_raw": "+3",
      "lower": "+3",
      "properties": []
    },
    "framesOnStartup": {
      "_raw": ",i18",
      "lower": "i18",
      "properties": []
    },
    "hitLevels": [
      "h",
      "h",
      "l"
    ],
    "index": 29,
    "input": "3,1,4",
    "name": "Kishin Rekko",
    "notes": [
      "Combo from 2nd CH with 9f delay",
      "Input can be delayed 14f",
      "Move can be delayed 12f"
    ],
    "specials": [],
    "state": {
      "_raw": ""
    }
  },
  {
    "damage": [
      15
    ],
    "framesOnBlock": {
      "_raw": "-9",
      "lower": "-9",
      "properties": []
    },
    "framesOnCounter": {
      "_raw": "+13c",
      "lower": "+13",
      "properties": [
        "c"
      ]
    },
    "framesOnHit": {
      "_raw": "+10g",
      "lower": "+10",
      "properties": [
        "g"
      ]
    },
    "framesOnStartup": {
      "_raw": "i13~14",
      "lower": "i13",
      "properties": [],
      "upper": "14"
    },
    "hitLevels": [
      "h"
    ],
    "index": 30,
    "input": "4",
    "name": "High Right Roundhouse",
    "notes": [],
    "specials": [
      "Homing",
      "Balcony Break"
    ],
    "state": {
      "_raw": ""
    }
  },
  {
    "damage": [
      27
    ],
    "framesOnBlock": {
      "_raw": "-11~-2",
      "lower": "-11",
      "properties": [],
      "upper": "-2"
    },
    "framesOnCounter": {
      "_raw": "",
      "lower": "",
      "properties": []
    },
    "framesOnHit": {
      "_raw": "+2a~+12a",
      "lower": "+2",
      "properties": [
        "a",
        "a"
      ],
      "upper": "+12"
    },
    "framesOnStartup": {
      "_raw": "i24~34",
      "lower": "i24",
      "properties": [],
      "upper": "34"
    },
    "hitLevels": [
      "m"
    ],
    "index": 31,
    "input": "4~3",
    "name": "Spinning Flare Kick",
    "notes": [],
    "specials": [
      "Spike"
    ],
    "state": {
      "_raw": ""
    }
  },
  {
    "damage": [
      12
    ],
    "framesOnBlock": {
      "_raw": "-16",
      "lower": "-16",
      "properties": []
    },
    "framesOnCounter": {
      "_raw": "",
      "lower": "",
      "properties": []
    },
    "framesOnHit": {
      "_raw": "-5",
      "lower": "-5",
      "properties": []
    },
    "framesOnStartup": {
      "_raw": "i14",
      "lower": "i14",
      "properties": []
    },
    "hitLevels": [
      "m"
    ],
    "index": 33,
    "input": "f+3",
    "name": "Left Sidekick",
    "notes": [],
    "specials": [],
    "state": {
      "_raw": ""
    }
  },
  {
    "damage": [
      12,
      14
    ],
    "framesOnBlock": {
      "_raw": "-8",
      "lower": "-8",
      "properties": []
    },
    "framesOnCounter": {
      "_raw": "",
      "lower": "",
      "properties": []
    },
    "framesOnHit": {
      "_raw": "+8",
      "lower": "+8",
      "properties": []
    },
    "framesOnStartup": {
      "_raw": ",i20",
      "lower": "i20",
      "properties": []
    },
    "hitLevels": [
      "m",
      "h"
    ],
    "index": 35,
    "input": "f+3,3",
    "name": "Left Sidekick > Stinger",
    "notes": [
      "Enter ZEN -7 +9 r26 with F",
      "Transition to backdash with B"
    ],
    "specials": [],
    "state": {
      "_raw": ""
    }
  },
  {
    "damage": [
      21
    ],
    "framesOnBlock": {
      "_raw": "-8",
      "lower": "-8",
      "properties": []
    },
    "framesOnCounter": {
      "_raw": "+42a",
      "lower": "+42",
      "properties": [
        "a"
      ]
    },
    "framesOnHit": {
      "_raw": "+4",
      "lower": "+4",
      "properties": []
    },
    "framesOnStartup": {
      "_raw": "i16-17",
      "lower": "i16",
      "properties": []
    },
    "hitLevels": [
      "m"
    ],
    "index": 36,
    "input": "f+4",
    "name": "Front Thrust Kick",
    "notes": [
      "Enter ZEN -1 +11 +49a r26 with F",
      "Balcony break on airborne hit"
    ],
    "specials": [],
    "state": {
      "_raw": ""
    }
  },
  {
    "damage": [
      14,
      24
    ],
    "framesOnBlock": {
      "_raw": "-6",
      "lower": "-6",
      "properties": []
    },
    "framesOnCounter": {
      "_raw": "",
      "lower": "",
      "properties": []
    },
    "framesOnHit": {
      "_raw": "+21a (+11)",
      "lower": "+21",
      "properties": [
        "a"
      ],
      "tech": "+11"
    },
    "framesOnStartup": {
      "_raw": "i14 i9~10",
      "lower": "i14",
      "properties": [],
      "upper": "10"
    },
    "hitLevels": [
      "h",
      "h"
    ],
    "index": 37,
    "input": "f+1+2",
    "name": "Double Chamber Punch",
    "notes": [
      "Jail from 1st attack",
      "Chip damage on block"
    ],
    "specials": [
      "Balcony Break"
    ],
    "state": {
      "_raw": ""
    }
  },
  {
    "damage": [
      10
    ],
    "framesOnBlock": {
      "_raw": "-3",
      "lower": "-3",
      "properties": []
    },
    "framesOnCounter": {
      "_raw": "+6",
      "lower": "+6",
      "properties": []
    },
    "framesOnHit": {
      "_raw": "+4",
      "lower": "+4",
      "properties": []
    },
    "framesOnStartup": {
      "_raw": "i13~14",
      "lower": "i13",
      "properties": [],
      "upper": "14"
    },
    "hitLevels": [
      "m"
    ],
    "index": 38,
    "input": "df+1",
    "name": "Mid Left Punch",
    "notes": [],
    "specials": [],
    "state": {
      "_raw": ""
    }
  },
  {
    "damage": [
      10,
      18
    ],
    "framesOnBlock": {
      "_raw": "-9",
      "lower": "-9",
      "properties": []
    },
    "framesOnCounter": {
      "_raw": "+17a (+8)",
      "lower": "+17",
      "properties": [
        "a"
      ],
      "tech": "+8"
    },
    "framesOnHit": {
      "_raw": "+10g",
      "lower": "+10",
      "properties": [
        "g"
      ]
    },
    "framesOnStartup": {
      "_raw": ",i18~21",
      "lower": "i18",
      "properties": [],
      "upper": "21"
    },
    "hitLevels": [
      "m",
      "h"
    ],
    "index": 39,
    "input": "df+1,4",
    "name": "Mid Left Punch > High Roundhouse Kick",
    "notes": [
      "Combo from 1st hit with 5f delay",
      "Input can be delayed 10f",
      "Move can be delayed 9f"
    ],
    "specials": [
      "Balcony Break"
    ],
    "state": {
      "_raw": ""
    }
  },
  {
    "damage": [
      10,
      24
    ],
    "framesOnBlock": {
      "_raw": "-12",
      "lower": "-12",
      "properties": []
    },
    "framesOnCounter": {
      "_raw": "",
      "lower": "",
      "properties": []
    },
    "framesOnHit": {
      "_raw": "+10a (+1)",
      "lower": "+10",
      "properties": [
        "a"
      ],
      "tech": "+1"
    },
    "framesOnStartup": {
      "_raw": ",i20",
      "lower": "i20",
      "properties": []
    },
    "hitLevels": [
      "m",
      "m"
    ],
    "index": 40,
    "input": "df+1,4~4",
    "name": "Mid Left Punch > Mid Sidekick",
    "notes": [],
    "specials": [
      "Balcony Break"
    ],
    "state": {
      "_raw": ""
    }
  },
  {
    "damage": [
      12
    ],
    "framesOnBlock": {
      "_raw": "-9",
      "lower": "-9",
      "properties": []
    },
    "framesOnCounter": {
      "_raw": "",
      "lower": "",
      "properties": []
    },
    "framesOnHit": {
      "_raw": "+6",
      "lower": "+6",
      "properties": []
    },
    "framesOnStartup": {
      "_raw": "i16~17",
      "lower": "i16",
      "properties": [],
      "upper": "17"
    },
    "hitLevels": [
      "m"
    ],
    "index": 41,
    "input": "df+2",
    "name": "Fiendish Rend",
    "notes": [
      "Enter Breaking Step -2 +13g r23 with df",
      "Chip damage on block"
    ],
    "specials": [
      "Balcony Break"
    ],
    "state": {
      "_raw": ""
    }
  },
  {
    "damage": [
      16
    ],
    "framesOnBlock": {
      "_raw": "-8",
      "lower": "-8",
      "properties": []
    },
    "framesOnCounter": {
      "_raw": "",
      "lower": "",
      "properties": []
    },
    "framesOnHit": {
      "_raw": "+3",
      "lower": "+3",
      "properties": []
    },
    "framesOnStartup": {
      "_raw": "i12",
      "lower": "i12",
      "properties": []
    },
    "hitLevels": [
      "m"
    ],
    "index": 42,
    "input": "df+3",
    "name": "Left Roundhouse",
    "notes": [],
    "specials": [],
    "state": {
      "_raw": ""
    }
  },
  {
    "damage": [
      20
    ],
    "framesOnBlock": {
      "_raw": "+6c",
      "lower": "+6",
      "properties": [
        "c"
      ]
    },
    "framesOnCounter": {
      "_raw": "",
      "lower": "",
      "properties": []
    },
    "framesOnHit": {
      "_raw": "+13c",
      "lower": "+13",
      "properties": [
        "c"
      ]
    },
    "framesOnStartup": {
      "_raw": "i23~i24",
      "lower": "i23",
      "properties": [],
      "upper": "i24"
    },
    "hitLevels": [
      "m"
    ],
    "index": 43,
    "input": "df+3~3",
    "name": "Brazilian Kick",
    "notes": [
      "Enter Breaking Step +2c +9c r27 with df"
    ],
    "specials": [
      "Spike"
    ],
    "state": {
      "_raw": ""
    }
  },
  {
    "damage": [
      21,
      10
    ],
    "framesOnBlock": {
      "_raw": "-13",
      "lower": "-13",
      "properties": []
    },
    "framesOnCounter": {
      "_raw": "",
      "lower": "",
      "properties": []
    },
    "framesOnHit": {
      "_raw": "+0d",
      "lower": "+0",
      "properties": [
        "d"
      ]
    },
    "framesOnStartup": {
      "_raw": "i21",
      "lower": "i21",
      "properties": []
    },
    "hitLevels": [
      "m",
      "t"
    ],
    "index": 45,
    "input": "d+1",
    "name": "Corpse Thrust > Black Wing Flash",
    "notes": [
      "Balcony break on airborne hit",
      "Transition to attack throw on standing hit",
      "-9 on block after absorbing an attack and 8 chip damage on block"
    ],
    "specials": [],
    "state": {
      "_raw": ""
    }
  },
  {
    "damage": [
      22
    ],
    "framesOnBlock": {
      "_raw": "-14",
      "lower": "-14",
      "properties": []
    },
    "framesOnCounter": {
      "_raw": "+71a (+55)",
      "lower": "+71",
      "properties": [
        "a"
      ],
      "tech": "+55"
    },
    "framesOnHit": {
      "_raw": "+4c",
      "lower": "+4",
      "properties": [
        "c"
      ]
    },
    "framesOnStartup": {
      "_raw": "i22~23",
      "lower": "i22",
      "properties": [],
      "upper": "23"
    },
    "hitLevels": [
      "L"
    ],
    "index": 46,
    "input": "d+2",
    "name": "Scourge",
    "notes": [
      "Balcony break on airborne hit"
    ],
    "specials": [],
    "state": {
      "_raw": ""
    }
  },
  {
    "damage": [
      7
    ],
    "framesOnBlock": {
      "_raw": "-14",
      "lower": "-14",
      "properties": []
    },
    "framesOnCounter": {
      "_raw": "",
      "lower": "",
      "properties": []
    },
    "framesOnHit": {
      "_raw": "-3",
      "lower": "-3",
      "properties": []
    },
    "framesOnStartup": {
      "_raw": "i15~16",
      "lower": "i15",
      "properties": [],
      "upper": "16"
    },
    "hitLevels": [
      "l"
    ],
    "index": 47,
    "input": "d+3",
    "name": "",
    "notes": [],
    "specials": [],
    "state": {
      "_raw": ""
    }
  },
  {
    "damage": [
      7,
      10
    ],
    "framesOnBlock": {
      "_raw": "-11",
      "lower": "-11",
      "properties": []
    },
    "framesOnCounter": {
      "_raw": "",
      "lower": "",
      "properties": []
    },
    "framesOnHit": {
      "_raw": "-3",
      "lower": "-3",
      "properties": []
    },
    "framesOnStartup": {
      "_raw": ",i20~21",
      "lower": "i20",
      "properties": [],
      "upper": "21"
    },
    "hitLevels": [
      "l",
      "h"
    ],
    "index": 48,
    "input": "d+3,4",
    "name": "",
    "notes": [],
    "specials": [],
    "state": {
      "_raw": ""
    }
  },
  {
    "damage": [
      7,
      10,
      21
    ],
    "framesOnBlock": {
      "_raw": "-12",
      "lower": "-12",
      "properties": []
    },
    "framesOnCounter": {
      "_raw": "",
      "lower": "",
      "properties": []
    },
    "framesOnHit": {
      "_raw": "+31d (+23)",
      "lower": "+31",
      "properties": [
        "d"
      ],
      "tech": "+23"
    },
    "framesOnStartup": {
      "_raw": ",i24~25",
      "lower": "i24",
      "properties": [],
      "upper": "25"
    },
    "hitLevels": [
      "l",
      "h",
      "m"
    ],
    "index": 49,
    "input": "d+3,4,3",
    "name": "Kazama Style Three-Quarter Kick",
    "notes": [
      "Combo from 2nd CH with 2f delay",
      "Input can be delayed 10f"
    ],
    "specials": [
      "Tornado",
      "Balcony Break"
    ],
    "state": {
      "_raw": ""
    }
  },
  {
    "damage": [
      7,
      24
    ],
    "framesOnBlock": {
      "_raw": "-12",
      "lower": "-12",
      "properties": []
    },
    "framesOnCounter": {
      "_raw": "",
      "lower": "",
      "properties": []
    },
    "framesOnHit": {
      "_raw": "+10a (+1)",
      "lower": "+10",
      "properties": [
        "a"
      ],
      "tech": "+1"
    },
    "framesOnStartup": {
      "_raw": ",i20",
      "lower": "i20",
      "properties": []
    },
    "hitLevels": [
      "l",
      "m"
    ],
    "index": 50,
    "input": "d+3,4~4",
    "name": "Knee Popper > Mid Sidekick",
    "notes": [],
    "specials": [
      "Balcony Break"
    ],
    "state": {
      "_raw": ""
    }
  },
  {
    "damage": [
      11
    ],
    "framesOnBlock": {
      "_raw": "-12",
      "lower": "-12",
      "properties": []
    },
    "framesOnCounter": {
      "_raw": "",
      "lower": "",
      "properties": []
    },
    "framesOnHit": {
      "_raw": "-1",
      "lower": "-1",
      "properties": []
    },
    "framesOnStartup": {
      "_raw": "i16~17",
      "lower": "i16",
      "properties": [],
      "upper": "17"
    },
    "hitLevels": [
      "L"
    ],
    "index": 51,
    "input": "d+4",
    "name": "Right Sweep",
    "notes": [],
    "specials": [],
    "state": {
      "_raw": ""
    }
  },
  {
    "damage": [
      5,
      15
    ],
    "framesOnBlock": {
      "_raw": "-19",
      "lower": "-19",
      "properties": []
    },
    "framesOnCounter": {
      "_raw": "",
      "lower": "",
      "properties": []
    },
    "framesOnHit": {
      "_raw": "+32a (+22)",
      "lower": "+32",
      "properties": [
        "a"
      ],
      "tech": "+22"
    },
    "framesOnStartup": {
      "_raw": "i15 i10~12",
      "lower": "i15",
      "properties": [],
      "upper": "12"
    },
    "hitLevels": [
      "m",
      "m"
    ],
    "index": 52,
    "input": "d+3+4",
    "name": "Double Lift Kick",
    "notes": [],
    "specials": [],
    "state": {
      "_raw": ""
    }
  },
  {
    "damage": [
      12
    ],
    "framesOnBlock": {
      "_raw": "-10",
      "lower": "-10",
      "properties": []
    },
    "framesOnCounter": {
      "_raw": "",
      "lower": "",
      "properties": []
    },
    "framesOnHit": {
      "_raw": "-4",
      "lower": "-4",
      "properties": []
    },
    "framesOnStartup": {
      "_raw": "i16",
      "lower": "i16",
      "properties": []
    },
    "hitLevels": [
      "m"
    ],
    "index": 53,
    "input": "db+2",
    "name": "",
    "notes": [],
    "specials": [],
    "state": {
      "_raw": ""
    }
  },
  {
    "damage": [
      12,
      11
    ],
    "framesOnBlock": {
      "_raw": "-12",
      "lower": "-12",
      "properties": []
    },
    "framesOnCounter": {
      "_raw": "+43a",
      "lower": "+43",
      "properties": [
        "a"
      ]
    },
    "framesOnHit": {
      "_raw": "-7",
      "lower": "-7",
      "properties": []
    },
    "framesOnStartup": {
      "_raw": ",i8",
      "lower": "i8",
      "properties": []
    },
    "hitLevels": [
      "m",
      "h"
    ],
    "index": 54,
    "input": "db+2,2",
    "name": "",
    "notes": [],
    "specials": [],
    "state": {
      "_raw": ""
    }
  },
  {
    "damage": [
      12,
      11,
      21
    ],
    "framesOnBlock": {
      "_raw": "-9",
      "lower": "-9",
      "properties": []
    },
    "framesOnCounter": {
      "_raw": "",
      "lower": "",
      "properties": []
    },
    "framesOnHit": {
      "_raw": "+20a",
      "lower": "+20",
      "properties": [
        "a"
      ]
    },
    "framesOnStartup": {
      "_raw": ",i35~i36",
      "lower": "i35",
      "properties": [],
      "upper": "i36"
    },
    "hitLevels": [
      "m",
      "h",
      "m"
    ],
    "index": 55,
    "input": "db+2,2,3",
    "name": "Savage Sword",
    "notes": [
      "Balcony break on airborne hit"
    ],
    "specials": [],
    "state": {
      "_raw": ""
    }
  },
  {
    "damage": [
      12,
      23
    ],
    "framesOnBlock": {
      "_raw": "-8",
      "lower": "-8",
      "properties": []
    },
    "framesOnCounter": {
      "_raw": "",
      "lower": "",
      "properties": []
    },
    "framesOnHit": {
      "_raw": "+7a",
      "lower": "+7",
      "properties": [
        "a"
      ]
    },
    "framesOnStartup": {
      "_raw": ",i27~i29",
      "lower": "i27",
      "properties": [],
      "upper": "i29"
    },
    "hitLevels": [
      "m",
      "M"
    ],
    "index": 56,
    "input": "db+2,3",
    "name": "Punch > Cascade Kick",
    "notes": [],
    "specials": [
      "Spike"
    ],
    "state": {
      "_raw": ""
    }
  },
  {
    "damage": [
      28
    ],
    "framesOnBlock": {
      "_raw": "-10~-8",
      "lower": "-10",
      "properties": [],
      "upper": "-8"
    },
    "framesOnCounter": {
      "_raw": "",
      "lower": "",
      "properties": []
    },
    "framesOnHit": {
      "_raw": "+17a",
      "lower": "+17",
      "properties": [
        "a"
      ]
    },
    "framesOnStartup": {
      "_raw": "i19~i21",
      "lower": "i19",
      "properties": [],
      "upper": "i21"
    },
    "hitLevels": [
      "h"
    ],
    "index": 57,
    "input": "db+3",
    "name": "Left Spinning Back Kick",
    "notes": [],
    "specials": [],
    "state": {
      "_raw": ""
    }
  },
  {
    "damage": [
      18
    ],
    "framesOnBlock": {
      "_raw": "-13",
      "lower": "-13",
      "properties": []
    },
    "framesOnCounter": {
      "_raw": "+13g",
      "lower": "+13",
      "properties": [
        "g"
      ]
    },
    "framesOnHit": {
      "_raw": "+3",
      "lower": "+3",
      "properties": []
    },
    "framesOnStartup": {
      "_raw": "i20~21",
      "lower": "i20",
      "properties": [],
      "upper": "21"
    },
    "hitLevels": [
      "l"
    ],
    "index": 58,
    "input": "db+4",
    "name": "Right Low Roundhouse",
    "notes": [],
    "specials": [],
    "state": {
      "_raw": ""
    }
  },
  {
    "damage": [
      0
    ],
    "framesOnBlock": {
      "_raw": "-11~+4",
      "lower": "-11",
      "properties": [],
      "upper": "+4"
    },
    "framesOnCounter": {
      "_raw": "",
      "lower": "",
      "properties": []
    },
    "framesOnHit": {
      "_raw": "+17g~+32g",
      "lower": "+17",
      "properties": [
        "g",
        "g"
      ],
      "upper": "+32"
    },
    "framesOnStartup": {
      "_raw": "i19~34",
      "lower": "i19",
      "properties": [],
      "upper": "34"
    },
    "hitLevels": [
      "M"
    ],
    "index": 59,
    "input": "db+1+2",
    "name": "Power Stance",
    "notes": [
      "+4a (-5) on BT hit",
      "Unparryable by traditional parries, Asuka, Nina, etc",
      "Opponent recovers crouching",
      "Power up in Heat"
    ],
    "specials": [
      "Balcony Break"
    ],
    "state": {
      "_raw": ""
    }
  },
  {
    "damage": [
      11
    ],
    "framesOnBlock": {
      "_raw": "-9",
      "lower": "-9",
      "properties": []
    },
    "framesOnCounter": {
      "_raw": "",
      "lower": "",
      "properties": []
    },
    "framesOnHit": {
      "_raw": "+2",
      "lower": "+2",
      "properties": []
    },
    "framesOnStartup": {
      "_raw": "i12",
      "lower": "i12",
      "properties": []
    },
    "hitLevels": [
      "h"
    ],
    "index": 60,
    "input": "b+1",
    "name": "",
    "notes": [],
    "specials": [],
    "state": {
      "_raw": ""
    }
  },
  {
    "damage": [
      11,
      20
    ],
    "framesOnBlock": {
      "_raw": "-10",
      "lower": "-10",
      "properties": []
    },
    "framesOnCounter": {
      "_raw": "",
      "lower": "",
      "properties": []
    },
    "framesOnHit": {
      "_raw": "+32a (+17)",
      "lower": "+32",
      "properties": [
        "a"
      ],
      "tech": "+17"
    },
    "framesOnStartup": {
      "_raw": ",i22~24",
      "lower": "i22",
      "properties": [],
      "upper": "24"
    },
    "hitLevels": [
      "h",
      "h"
    ],
    "index": 61,
    "input": "b+1,2",
    "name": "Shun Maten",
    "notes": [
      "Combo from 1st hit with 8f delay"
    ],
    "specials": [
      "Tornado"
    ],
    "state": {
      "_raw": ""
    }
  },
  {
    "damage": [
      12
    ],
    "framesOnBlock": {
      "_raw": "-11",
      "lower": "-11",
      "properties": []
    },
    "framesOnCounter": {
      "_raw": "",
      "lower": "",
      "properties": []
    },
    "framesOnHit": {
      "_raw": "+0",
      "lower": "+0",
      "properties": []
    },
    "framesOnStartup": {
      "_raw": "i15~16",
      "lower": "i15",
      "properties": [],
      "upper": "16"
    },
    "hitLevels": [
      "m"
    ],
    "index": 62,
    "input": "b+2",
    "name": "",
    "notes": [],
    "specials": [],
    "state": {
      "_raw": ""
    }
  },
  {
    "damage": [
      12,
      10
    ],
    "framesOnBlock": {
      "_raw": "-9",
      "lower": "-9",
      "properties": []
    },
    "framesOnCounter": {
      "_raw": "",
      "lower": "",
      "properties": []
    },
    "framesOnHit": {
      "_raw": "+2",
      "lower": "+2",
      "properties": []
    },
    "framesOnStartup": {
      "_raw": ",i14~15",
      "lower": "i14",
      "properties": [],
      "upper": "15"
    },
    "hitLevels": [
      "m",
      "m"
    ],
    "index": 63,
    "input": "b+2,1",
    "name": "Shun Masatsu",
    "notes": [
      "Combo from 1st hit with 1f delay",
      "Combo from 1st CH with 13f delay"
    ],
    "specials": [],
    "state": {
      "_raw": ""
    }
  },
  {
    "damage": [
      17
    ],
    "framesOnBlock": {
      "_raw": "-6",
      "lower": "-6",
      "properties": []
    },
    "framesOnCounter": {
      "_raw": "",
      "lower": "",
      "properties": []
    },
    "framesOnHit": {
      "_raw": "+5",
      "lower": "+5",
      "properties": []
    },
    "framesOnStartup": {
      "_raw": "i16",
      "lower": "i16",
      "properties": []
    },
    "hitLevels": [
      "m"
    ],
    "index": 64,
    "input": "b+3",
    "name": "Left Knee",
    "notes": [
      "Enter ZEN -2 +9 r20 with F"
    ],
    "specials": [
      "Knee"
    ],
    "state": {
      "_raw": ""
    }
  },
  {
    "damage": [
      17,
      20
    ],
    "framesOnBlock": {
      "_raw": "-9",
      "lower": "-9",
      "properties": []
    },
    "framesOnCounter": {
      "_raw": "",
      "lower": "",
      "properties": []
    },
    "framesOnHit": {
      "_raw": "+9g +21w",
      "lower": "+9",
      "properties": [
        "g"
      ]
    },
    "framesOnStartup": {
      "_raw": ",i19~20",
      "lower": "i19",
      "properties": [],
      "upper": "20"
    },
    "hitLevels": [
      "m",
      "m"
    ],
    "index": 65,
    "input": "b+3,2",
    "name": "Left Knee > Right Thrust",
    "notes": [
      "Balcony break on airborne hit"
    ],
    "specials": [
      "Wall Crush +21g on hit"
    ],
    "state": {
      "_raw": ""
    }
  },
  {
    "damage": [
      21
    ],
    "framesOnBlock": {
      "_raw": "-7",
      "lower": "-7",
      "properties": []
    },
    "framesOnCounter": {
      "_raw": "",
      "lower": "",
      "properties": []
    },
    "framesOnHit": {
      "_raw": "+15a",
      "lower": "+15",
      "properties": [
        "a"
      ]
    },
    "framesOnStartup": {
      "_raw": "i17~18",
      "lower": "i17",
      "properties": [],
      "upper": "18"
    },
    "hitLevels": [
      "m"
    ],
    "index": 66,
    "input": "b+4",
    "name": "Spinning Sidekick",
    "notes": [],
    "specials": [
      "Balcony Break"
    ],
    "state": {
      "_raw": ""
    }
  },
  {
    "damage": [
      20
    ],
    "framesOnBlock": {
      "_raw": "-12",
      "lower": "-12",
      "properties": []
    },
    "framesOnCounter": {
      "_raw": "",
      "lower": "",
      "properties": []
    },
    "framesOnHit": {
      "_raw": "+6",
      "lower": "+6",
      "properties": []
    },
    "framesOnStartup": {
      "_raw": "i23~24",
      "lower": "i23",
      "properties": [],
      "upper": "24"
    },
    "hitLevels": [
      "m"
    ],
    "index": 67,
    "input": "b+1+2",
    "name": "Suigetsu Strike",
    "notes": [],
    "specials": [],
    "state": {
      "_raw": ""
    }
  },
  {
    "damage": [],
    "framesOnBlock": {
      "_raw": "",
      "lower": "",
      "properties": []
    },
    "framesOnCounter": {
      "_raw": "",
      "lower": "",
      "properties": []
    },
    "framesOnHit": {
      "_raw": "",
      "lower": "",
      "properties": []
    },
    "framesOnStartup": {
      "_raw": "",
      "lower": "",
      "properties": []
    },
    "hitLevels": [],
    "index": 68,
    "input": "b+3+4",
    "name": "\nZanshin\nCrouching Demon Stance (CDS)\nMental Alertness (2)\n",
    "notes": [
      "Can perform all attacks from ZEN Stance",
      "Enter Breaking Step with DF",
      "Cancel on any frame with f",
      "Transition to dash with f",
      "Steps backward",
      "Actionable after 5f"
    ],
    "specials": [],
    "state": {
      "_raw": ""
    }
  },
  {
    "damage": [
      15
    ],
    "framesOnBlock": {
      "_raw": "-13",
      "lower": "-13",
      "properties": []
    },
    "framesOnCounter": {
      "_raw": "+33a (+23a)",
      "lower": "+33",
      "properties": [
        "a"
      ]
    },
    "framesOnHit": {
      "_raw": "+19a (+9)",
      "lower": "+19",
      "properties": [
        "a"
      ],
      "tech": "+9"
    },
    "framesOnStartup": {
      "_raw": "i15~17",
      "lower": "i15",
      "properties": [],
      "upper": "17"
    },
    "hitLevels": [
      "m"
    ],
    "index": 69,
    "input": "ub+4",
    "name": "",
    "notes": [],
    "specials": [
      "Balcony Break"
    ],
    "state": {
      "_raw": ""
    }
  },
  {
    "damage": [
      50
    ],
    "framesOnBlock": {
      "_raw": "",
      "lower": "",
      "properties": []
    },
    "framesOnCounter": {
      "_raw": "",
      "lower": "",
      "properties": []
    },
    "framesOnHit": {
      "_raw": "+9a (+0)",
      "lower": "+9",
      "properties": [
        "a"
      ],
      "tech": "+0"
    },
    "framesOnStartup": {
      "_raw": "i75~i76",
      "lower": "i75",
      "properties": [],
      "upper": "i76"
    },
    "hitLevels": [
      "m!"
    ],
    "index": 70,
    "input": "ub+1+2",
    "name": "\nAvenger\nKonshin Seikenzuki\n",
    "notes": [
      "Cancel to r50 with b,b"
    ],
    "specials": [
      "Balcony Break"
    ],
    "state": {
      "_raw": ""
    }
  },
  {
    "damage": [
      18
    ],
    "framesOnBlock": {
      "_raw": "-7~-6",
      "lower": "-7",
      "properties": [],
      "upper": "-6"
    },
    "framesOnCounter": {
      "_raw": "+19a (+10)",
      "lower": "+19",
      "properties": [
        "a"
      ],
      "tech": "+10"
    },
    "framesOnHit": {
      "_raw": "+6~+7",
      "lower": "+6",
      "properties": [],
      "upper": "+7"
    },
    "framesOnStartup": {
      "_raw": "i15~i16",
      "lower": "i15",
      "properties": [],
      "upper": "i16"
    },
    "hitLevels": [
      "m"
    ],
    "index": 71,
    "input": "uf+2",
    "name": "Evading Middle Strike",
    "notes": [
      "Balcony break on CH",
      "Evasive, can avoid some attacks due to built-in sidestep"
    ],
    "specials": [],
    "state": {
      "_raw": ""
    }
  },
  {
    "damage": [
      17
    ],
    "framesOnBlock": {
      "_raw": "-9",
      "lower": "-9",
      "properties": []
    },
    "framesOnCounter": {
      "_raw": "+59a",
      "lower": "+59",
      "properties": [
        "a"
      ]
    },
    "framesOnHit": {
      "_raw": "+6",
      "lower": "+6",
      "properties": []
    },
    "framesOnStartup": {
      "_raw": "i22~23",
      "lower": "i22",
      "properties": [],
      "upper": "23"
    },
    "hitLevels": [
      "m"
    ],
    "index": 72,
    "input": "uf+3",
    "name": "Left Spinning Jump Kick",
    "notes": [],
    "specials": [],
    "state": {
      "_raw": ""
    }
  },
  {
    "damage": [
      13
    ],
    "framesOnBlock": {
      "_raw": "-13",
      "lower": "-13",
      "properties": []
    },
    "framesOnCounter": {
      "_raw": "",
      "lower": "",
      "properties": []
    },
    "framesOnHit": {
      "_raw": "+33a (+23a)",
      "lower": "+33",
      "properties": [
        "a"
      ]
    },
    "framesOnStartup": {
      "_raw": "i15~17",
      "lower": "i15",
      "properties": [],
      "upper": "17"
    },
    "hitLevels": [
      "m"
    ],
    "index": 73,
    "input": "uf+4",
    "name": "Front Jump Kick",
    "notes": [],
    "specials": [],
    "state": {
      "_raw": ""
    }
  },
  {
    "damage": [
      20
    ],
    "framesOnBlock": {
      "_raw": "-13",
      "lower": "-13",
      "properties": []
    },
    "framesOnCounter": {
      "_raw": "",
      "lower": "",
      "properties": []
    },
    "framesOnHit": {
      "_raw": "+32a (+22a)",
      "lower": "+32",
      "properties": [
        "a"
      ]
    },
    "framesOnStartup": {
      "_raw": "i23~i25",
      "lower": "i23",
      "properties": [],
      "upper": "i25"
    },
    "hitLevels": [
      "m"
    ],
    "index": 74,
    "input": "uf,n,4",
    "name": "Delayed Rising Toe Kick",
    "notes": [],
    "specials": [],
    "state": {
      "_raw": ""
    }
  },
  {
    "damage": [
      20
    ],
    "framesOnBlock": {
      "_raw": "-4",
      "lower": "-4",
      "properties": []
    },
    "framesOnCounter": {
      "_raw": "",
      "lower": "",
      "properties": []
    },
    "framesOnHit": {
      "_raw": "+24a",
      "lower": "+24",
      "properties": [
        "a"
      ]
    },
    "framesOnStartup": {
      "_raw": "i23~i25",
      "lower": "i23",
      "properties": [],
      "upper": "i25"
    },
    "hitLevels": [
      "m"
    ],
    "index": 76,
    "input": "f,F+3",
    "name": "Left Axe Kick",
    "notes": [
      "Cannot be buffered"
    ],
    "specials": [
      "Spike"
    ],
    "state": {
      "_raw": ""
    }
  },
  {
    "damage": [
      20,
      5
    ],
    "framesOnBlock": {
      "_raw": "+1",
      "lower": "+1",
      "properties": []
    },
    "framesOnCounter": {
      "_raw": "",
      "lower": "",
      "properties": []
    },
    "framesOnHit": {
      "_raw": "+7",
      "lower": "+7",
      "properties": []
    },
    "framesOnStartup": {
      "_raw": ",i15",
      "lower": "i15",
      "properties": []
    },
    "hitLevels": [
      "m",
      "h"
    ],
    "index": 77,
    "input": "f,F+3,1",
    "name": "Left Axe Kick > Left Jab",
    "notes": [
      "Links to 1 jab extensions (e.g. f,F+3,1,2,4)"
    ],
    "specials": [],
    "state": {
      "_raw": ""
    }
  },
  {
    "damage": [
      28
    ],
    "framesOnBlock": {
      "_raw": "-7",
      "lower": "-7",
      "properties": []
    },
    "framesOnCounter": {
      "_raw": "",
      "lower": "",
      "properties": []
    },
    "framesOnHit": {
      "_raw": "+22a (+12)",
      "lower": "+22",
      "properties": [
        "a"
      ],
      "tech": "+12"
    },
    "framesOnStartup": {
      "_raw": "i17~i18",
      "lower": "i17",
      "properties": [],
      "upper": "i18"
    },
    "hitLevels": [
      "m"
    ],
    "index": 78,
    "input": "f,F+4",
    "name": "Battery Sidekick",
    "notes": [],
    "specials": [
      "Balcony Break"
    ],
    "state": {
      "_raw": ""
    }
  },
  {
    "damage": [
      15
    ],
    "framesOnBlock": {
      "_raw": "-7",
      "lower": "-7",
      "properties": []
    },
    "framesOnCounter": {
      "_raw": "",
      "lower": "",
      "properties": []
    },
    "framesOnHit": {
      "_raw": "+4",
      "lower": "+4",
      "properties": []
    },
    "framesOnStartup": {
      "_raw": "i15~i16",
      "lower": "i15",
      "properties": [],
      "upper": "i16"
    },
    "hitLevels": [
      "m"
    ],
    "index": 79,
    "input": "b,f+2",
    "name": "",
    "notes": [],
    "specials": [],
    "state": {
      "_raw": ""
    }
  },
  {
    "damage": [
      15,
      14
    ],
    "framesOnBlock": {
      "_raw": "-5",
      "lower": "-5",
      "properties": []
    },
    "framesOnCounter": {
      "_raw": "+9",
      "lower": "+9",
      "properties": []
    },
    "framesOnHit": {
      "_raw": "+6",
      "lower": "+6",
      "properties": []
    },
    "framesOnStartup": {
      "_raw": ",i21",
      "lower": "i21",
      "properties": []
    },
    "hitLevels": [
      "m",
      "h"
    ],
    "index": 80,
    "input": "b,f+2,1",
    "name": "",
    "notes": [
      "Combo from 1st hit with 8f delay",
      "Input can be delayed 12f"
    ],
    "specials": [],
    "state": {
      "_raw": ""
    }
  },
  {
    "damage": [
      15,
      14,
      20
    ],
    "framesOnBlock": {
      "_raw": "-5",
      "lower": "-5",
      "properties": []
    },
    "framesOnCounter": {
      "_raw": "+50a (+3)",
      "lower": "+50",
      "properties": [
        "a"
      ],
      "tech": "+3"
    },
    "framesOnHit": {
      "_raw": "+18a (+9)",
      "lower": "+18",
      "properties": [
        "a"
      ],
      "tech": "+9"
    },
    "framesOnStartup": {
      "_raw": ",i19~20",
      "lower": "i19",
      "properties": [],
      "upper": "20"
    },
    "hitLevels": [
      "m",
      "h",
      "m"
    ],
    "index": 81,
    "input": "b,f+2,1,2",
    "name": "Evil Intent",
    "notes": [
      "Combo from 2nd CH with 15f",
      "Input can be delayed 16f",
      "Move can be delayed 10f"
    ],
    "specials": [
      "Balcony Break"
    ],
    "state": {
      "_raw": ""
    }
  },
  {
    "damage": [
      15,
      14,
      22
    ],
    "framesOnBlock": {
      "_raw": "-14",
      "lower": "-14",
      "properties": []
    },
    "framesOnCounter": {
      "_raw": "",
      "lower": "",
      "properties": []
    },
    "framesOnHit": {
      "_raw": "+37a (+27)",
      "lower": "+37",
      "properties": [
        "a"
      ],
      "tech": "+27"
    },
    "framesOnStartup": {
      "_raw": ",i28~29",
      "lower": "i28",
      "properties": [],
      "upper": "29"
    },
    "hitLevels": [
      "m",
      "h",
      "M"
    ],
    "index": 82,
    "input": "b,f+2,1,df+2",
    "name": "Geyser",
    "notes": [
      "Combo from 2nd CH",
      "Input can be delayed 16f",
      "Move can be delayed 10f"
    ],
    "specials": [
      "Tornado"
    ],
    "state": {
      "_raw": ""
    }
  },
  {
    "damage": [
      15,
      17
    ],
    "framesOnBlock": {
      "_raw": "-9",
      "lower": "-9",
      "properties": []
    },
    "framesOnCounter": {
      "_raw": "+59a",
      "lower": "+59",
      "properties": [
        "a"
      ]
    },
    "framesOnHit": {
      "_raw": "+6",
      "lower": "+6",
      "properties": []
    },
    "framesOnStartup": {
      "_raw": ",i25",
      "lower": "i25",
      "properties": []
    },
    "hitLevels": [
      "m",
      "m"
    ],
    "index": 83,
    "input": "b,f+2,3",
    "name": "Keito",
    "notes": [
      "Combo from 1st hit with 4f delay",
      "Input can be delayed 9f",
      "Enter ZEN +2 +17g +71a r20 with F"
    ],
    "specials": [],
    "state": {
      "_raw": ""
    }
  },
  {
    "damage": [
      30
    ],
    "framesOnBlock": {
      "_raw": "+6",
      "lower": "+6",
      "properties": []
    },
    "framesOnCounter": {
      "_raw": "",
      "lower": "",
      "properties": []
    },
    "framesOnHit": {
      "_raw": "+13a~+14a (+3~+4)",
      "lower": "+13",
      "properties": [
        "a",
        "a"
      ],
      "upper": "+14"
    },
    "framesOnStartup": {
      "_raw": "i22~i23",
      "lower": "i22",
      "properties": [],
      "upper": "i23"
    },
    "hitLevels": [
      "m"
    ],
    "index": 84,
    "input": "f,f,F+3",
    "name": "Leaping Side Kick",
    "notes": [
      "Chip damage on block"
    ],
    "specials": [
      "Balcony Break"
    ],
    "state": {
      "_raw": ""
    }
  },
  {
    "damage": [
      20
    ],
    "framesOnBlock": {
      "_raw": "-26",
      "lower": "-26",
      "properties": []
    },
    "framesOnCounter": {
      "_raw": "",
      "lower": "",
      "properties": []
    },
    "framesOnHit": {
      "_raw": "+22a",
      "lower": "+22",
      "properties": [
        "a"
      ]
    },
    "framesOnStartup": {
      "_raw": "i25~i26",
      "lower": "i25",
      "properties": [],
      "upper": "i26"
    },
    "hitLevels": [
      "L"
    ],
    "index": 85,
    "input": "FC.df+4",
    "name": "Right Sweep (2)",
    "notes": [],
    "specials": [],
    "state": {
      "_raw": ""
    }
  },
  {
    "damage": [
      7
    ],
    "framesOnBlock": {
      "_raw": "-6",
      "lower": "-6",
      "properties": []
    },
    "framesOnCounter": {
      "_raw": "",
      "lower": "",
      "properties": []
    },
    "framesOnHit": {
      "_raw": "+5",
      "lower": "+5",
      "properties": []
    },
    "framesOnStartup": {
      "_raw": "i13~i14",
      "lower": "i13",
      "properties": [],
      "upper": "i14"
    },
    "hitLevels": [
      "m"
    ],
    "index": 86,
    "input": "ws1",
    "name": "",
    "notes": [],
    "specials": [],
    "state": {
      "_raw": ""
    }
  },
  {
    "damage": [
      7,
      19
    ],
    "framesOnBlock": {
      "_raw": "-8",
      "lower": "-8",
      "properties": []
    },
    "framesOnCounter": {
      "_raw": "",
      "lower": "",
      "properties": []
    },
    "framesOnHit": {
      "_raw": "+3c",
      "lower": "+3",
      "properties": [
        "c"
      ]
    },
    "framesOnStartup": {
      "_raw": ",i19~20",
      "lower": "i19",
      "properties": [],
      "upper": "20"
    },
    "hitLevels": [
      "m",
      "m"
    ],
    "index": 87,
    "input": "ws1,2",
    "name": "Twin Lancer",
    "notes": [
      "Combo from 1st hit with 1f delay",
      "Combo from 1st CH with 10f delay",
      "Input can be delayed 13f",
      "Enter ZEN -9 +2 r27 with F"
    ],
    "specials": [
      "Spike"
    ],
    "state": {
      "_raw": ""
    }
  },
  {
    "damage": [
      7,
      8
    ],
    "framesOnBlock": {
      "_raw": "-6",
      "lower": "-6",
      "properties": []
    },
    "framesOnCounter": {
      "_raw": "",
      "lower": "",
      "properties": []
    },
    "framesOnHit": {
      "_raw": "+4",
      "lower": "+4",
      "properties": []
    },
    "framesOnStartup": {
      "_raw": ",i14",
      "lower": "i14",
      "properties": []
    },
    "hitLevels": [
      "m",
      "h"
    ],
    "index": 88,
    "input": "ws1,3",
    "name": "",
    "notes": [
      "Jail from 1st attack",
      "Transition to r25 backdash with B"
    ],
    "specials": [],
    "state": {
      "_raw": ""
    }
  },
  {
    "damage": [
      7,
      8,
      4
    ],
    "framesOnBlock": {
      "_raw": "-11",
      "lower": "-11",
      "properties": []
    },
    "framesOnCounter": {
      "_raw": "",
      "lower": "",
      "properties": []
    },
    "framesOnHit": {
      "_raw": "-6",
      "lower": "-6",
      "properties": []
    },
    "framesOnStartup": {
      "_raw": ",i18",
      "lower": "i18",
      "properties": []
    },
    "hitLevels": [
      "m",
      "h",
      "m"
    ],
    "index": 89,
    "input": "ws1,3,2",
    "name": "",
    "notes": [],
    "specials": [],
    "state": {
      "_raw": ""
    }
  },
  {
    "damage": [
      7,
      8,
      4,
      3
    ],
    "framesOnBlock": {
      "_raw": "-11",
      "lower": "-11",
      "properties": []
    },
    "framesOnCounter": {
      "_raw": "",
      "lower": "",
      "properties": []
    },
    "framesOnHit": {
      "_raw": "+3",
      "lower": "+3",
      "properties": []
    },
    "framesOnStartup": {
      "_raw": ",i10",
      "lower": "i10",
      "properties": []
    },
    "hitLevels": [
      "m",
      "h",
      "m",
      "m"
    ],
    "index": 90,
    "input": "ws1,3,2,1",
    "name": "",
    "notes": [],
    "specials": [],
    "state": {
      "_raw": ""
    }
  },
  {
    "damage": [
      7,
      8,
      4,
      3,
      5
    ],
    "framesOnBlock": {
      "_raw": "-31",
      "lower": "-31",
      "properties": []
    },
    "framesOnCounter": {
      "_raw": "",
      "lower": "",
      "properties": []
    },
    "framesOnHit": {
      "_raw": "+8",
      "lower": "+8",
      "properties": []
    },
    "framesOnStartup": {
      "_raw": ",i20~21",
      "lower": "i20",
      "properties": [],
      "upper": "21"
    },
    "hitLevels": [
      "m",
      "h",
      "m",
      "m",
      "l"
    ],
    "index": 91,
    "input": "ws1,3,2,1,4",
    "name": "",
    "notes": [],
    "specials": [],
    "state": {
      "_raw": ""
    }
  },
  {
    "damage": [
      7,
      8,
      4,
      3,
      5,
      10
    ],
    "framesOnBlock": {
      "_raw": "-16",
      "lower": "-16",
      "properties": []
    },
    "framesOnCounter": {
      "_raw": "",
      "lower": "",
      "properties": []
    },
    "framesOnHit": {
      "_raw": "-8",
      "lower": "-8",
      "properties": []
    },
    "framesOnStartup": {
      "_raw": ",i31~32",
      "lower": "i31",
      "properties": [],
      "upper": "32"
    },
    "hitLevels": [
      "m",
      "h",
      "m",
      "m",
      "l",
      "M"
    ],
    "index": 92,
    "input": "ws1,3,2,1,4,2",
    "name": "Kazama Style 6 Hit Combo Redux",
    "notes": [
      "Combo from 1st hit"
    ],
    "specials": [
      "Spike"
    ],
    "state": {
      "_raw": ""
    }
  },
  {
    "damage": [
      7,
      20
    ],
    "framesOnBlock": {
      "_raw": "+6",
      "lower": "+6",
      "properties": []
    },
    "framesOnCounter": {
      "_raw": "",
      "lower": "",
      "properties": []
    },
    "framesOnHit": {
      "_raw": "+13c",
      "lower": "+13",
      "properties": [
        "c"
      ]
    },
    "framesOnStartup": {
      "_raw": ",i23~i24",
      "lower": "i23",
      "properties": [],
      "upper": "i24"
    },
    "hitLevels": [
      "m",
      "m"
    ],
    "index": 93,
    "input": "ws1,3~3",
    "name": "Solar Plexus Strike > Brazilian Kick",
    "notes": [
      "Enter Breaking Step +2 +9c with DF",
      "+16a on BT hit"
    ],
    "specials": [
      "Spike"
    ],
    "state": {
      "_raw": ""
    }
  },
  {
    "damage": [
      14
    ],
    "framesOnBlock": {
      "_raw": "-12",
      "lower": "-12",
      "properties": []
    },
    "framesOnCounter": {
      "_raw": "",
      "lower": "",
      "properties": []
    },
    "framesOnHit": {
      "_raw": "+39a (+29)",
      "lower": "+39",
      "properties": [
        "a"
      ],
      "tech": "+29"
    },
    "framesOnStartup": {
      "_raw": "i14~15",
      "lower": "i14",
      "properties": [],
      "upper": "15"
    },
    "hitLevels": [
      "m"
    ],
    "index": 94,
    "input": "ws2",
    "name": "Crouching Uppercut",
    "notes": [],
    "specials": [],
    "state": {
      "_raw": ""
    }
  },
  {
    "damage": [
      20
    ],
    "framesOnBlock": {
      "_raw": "-9",
      "lower": "-9",
      "properties": []
    },
    "framesOnCounter": {
      "_raw": "+22a",
      "lower": "+22",
      "properties": [
        "a"
      ]
    },
    "framesOnHit": {
      "_raw": "+10g",
      "lower": "+10",
      "properties": [
        "g"
      ]
    },
    "framesOnStartup": {
      "_raw": "i16~18",
      "lower": "i16",
      "properties": [],
      "upper": "18"
    },
    "hitLevels": [
      "m"
    ],
    "index": 95,
    "input": "ws3",
    "name": "Bamboo Splitter",
    "notes": [],
    "specials": [
      "Homing",
      "Balcony Break"
    ],
    "state": {
      "_raw": ""
    }
  },
  {
    "damage": [
      13
    ],
    "framesOnBlock": {
      "_raw": "-3",
      "lower": "-3",
      "properties": []
    },
    "framesOnCounter": {
      "_raw": "",
      "lower": "",
      "properties": []
    },
    "framesOnHit": {
      "_raw": "+8",
      "lower": "+8",
      "properties": []
    },
    "framesOnStartup": {
      "_raw": "i11~12",
      "lower": "i11",
      "properties": [],
      "upper": "12"
    },
    "hitLevels": [
      "m"
    ],
    "index": 96,
    "input": "ws4",
    "name": "",
    "notes": [],
    "specials": [],
    "state": {
      "_raw": ""
    }
  },
  {
    "damage": [
      13,
      15
    ],
    "framesOnBlock": {
      "_raw": "-7",
      "lower": "-7",
      "properties": []
    },
    "framesOnCounter": {
      "_raw": "",
      "lower": "",
      "properties": []
    },
    "framesOnHit": {
      "_raw": "+4",
      "lower": "+4",
      "properties": []
    },
    "framesOnStartup": {
      "_raw": ",i19~20",
      "lower": "i19",
      "properties": [],
      "upper": "20"
    },
    "hitLevels": [
      "m",
      "h"
    ],
    "index": 97,
    "input": "ws4,4",
    "name": "Double Cross Kicks",
    "notes": [
      "Combo from 1st hit with 1f delay"
    ],
    "specials": [],
    "state": {
      "_raw": ""
    }
  },
  {
    "damage": [],
    "framesOnBlock": {
      "_raw": "",
      "lower": "",
      "properties": []
    },
    "framesOnCounter": {
      "_raw": "",
      "lower": "",
      "properties": []
    },
    "framesOnHit": {
      "_raw": "",
      "lower": "",
      "properties": []
    },
    "framesOnStartup": {
      "_raw": "",
      "lower": "",
      "properties": []
    },
    "hitLevels": [],
    "index": 98,
    "input": "f,n,d,df",
    "name": "\nCrouch Dash\nBreaking Step\n",
    "notes": [
      "Cannot be buffered",
      "Stance moves can be buffered out of heat dash",
      "Cancel to sidestep with u",
      "Cancel to block with b"
    ],
    "specials": [],
    "state": {
      "_raw": ""
    }
  },
  {
    "damage": [],
    "framesOnBlock": {
      "_raw": "",
      "lower": "",
      "properties": []
    },
    "framesOnCounter": {
      "_raw": "",
      "lower": "",
      "properties": []
    },
    "framesOnHit": {
      "_raw": "",
      "lower": "",
      "properties": []
    },
    "framesOnStartup": {
      "_raw": "",
      "lower": "",
      "properties": []
    },
    "hitLevels": [],
    "index": 99,
    "input": "f,n,d,df,UF",
    "name": "",
    "notes": [
      "Can access wr3 by inputting 3 on frames 1~2",
      "Can access uf1+2 by inputting 1+2 on frames 1~2",
      "Unable to act from frames 3~26"
    ],
    "specials": [],
    "state": {
      "_raw": ""
    }
  },
  {
    "damage": [
      20
    ],
    "framesOnBlock": {
      "_raw": "-13",
      "lower": "-13",
      "properties": []
    },
    "framesOnCounter": {
      "_raw": "",
      "lower": "",
      "properties": []
    },
    "framesOnHit": {
      "_raw": "+32a (+22)",
      "lower": "+32",
      "properties": [
        "a"
      ],
      "tech": "+22"
    },
    "framesOnStartup": {
      "_raw": "i16~i17",
      "lower": "i16",
      "properties": [],
      "upper": "i17"
    },
    "hitLevels": [
      "m"
    ],
    "index": 100,
    "input": "CD.df+1",
    "name": "Thrusting Uppercut",
    "notes": [
      "Turns into CD.df#1 while in heat"
    ],
    "specials": [
      "Tornado"
    ],
    "state": {
      "_raw": ""
    }
  },
  {
    "damage": [
      22
    ],
    "framesOnBlock": {
      "_raw": "-13",
      "lower": "-13",
      "properties": []
    },
    "framesOnCounter": {
      "_raw": "",
      "lower": "",
      "properties": []
    },
    "framesOnHit": {
      "_raw": "+36a (+26)",
      "lower": "+36",
      "properties": [
        "a"
      ],
      "tech": "+26"
    },
    "framesOnStartup": {
      "_raw": "i16~i17",
      "lower": "i16",
      "properties": [],
      "upper": "i17"
    },
    "hitLevels": [
      "M"
    ],
    "index": 101,
    "input": "CD.df#1",
    "name": "Electric Thrusting Uppercut",
    "notes": [
      "Chip damage on block",
      "f,n,d,d#1",
      "ECD+1"
    ],
    "specials": [
      "Tornado"
    ],
    "state": {
      "_raw": ""
    }
  },
  {
    "damage": [
      20
    ],
    "framesOnBlock": {
      "_raw": "-10",
      "lower": "-10",
      "properties": []
    },
    "framesOnCounter": {
      "_raw": "",
      "lower": "",
      "properties": []
    },
    "framesOnHit": {
      "_raw": "+74a (+58)",
      "lower": "+74",
      "properties": [
        "a"
      ],
      "tech": "+58"
    },
    "framesOnStartup": {
      "_raw": "i11~12",
      "lower": "i11",
      "properties": [],
      "upper": "12"
    },
    "hitLevels": [
      "h"
    ],
    "index": 102,
    "input": "CD.df+2",
    "name": "Wind Hook Fist",
    "notes": [
      "Turns into EWHF (CD.df#2) while in heat",
      "WHF",
      "f,n,d,df+2"
    ],
    "specials": [
      "Balcony Break"
    ],
    "state": {
      "_raw": ""
    }
  },
  {
    "damage": [
      25
    ],
    "framesOnBlock": {
      "_raw": "+5~+6",
      "lower": "+5",
      "properties": [],
      "upper": "+6"
    },
    "framesOnCounter": {
      "_raw": "",
      "lower": "",
      "properties": []
    },
    "framesOnHit": {
      "_raw": "+76a (+60)",
      "lower": "+76",
      "properties": [
        "a"
      ],
      "tech": "+60"
    },
    "framesOnStartup": {
      "_raw": "i11~i12",
      "lower": "i11",
      "properties": [],
      "upper": "i12"
    },
    "hitLevels": [
      "h"
    ],
    "index": 103,
    "input": "CD.df#2",
    "name": "Electric Wind Hook Fist",
    "notes": [
      "Recovers 3f faster on hit or block (t36 r24)",
      "EWHF",
      "Electric",
      "ECD+2",
      "f,n,d,df#2"
    ],
    "specials": [
      "Balcony Break"
    ],
    "state": {
      "_raw": ""
    }
  },
  {
    "damage": [
      12
    ],
    "framesOnBlock": {
      "_raw": "-31",
      "lower": "-31",
      "properties": []
    },
    "framesOnCounter": {
      "_raw": "",
      "lower": "",
      "properties": []
    },
    "framesOnHit": {
      "_raw": "+8c",
      "lower": "+8",
      "properties": [
        "c"
      ]
    },
    "framesOnStartup": {
      "_raw": "i20~i21",
      "lower": "i20",
      "properties": [],
      "upper": "i21"
    },
    "hitLevels": [
      "l"
    ],
    "index": 104,
    "input": "CD.DF+4",
    "name": "",
    "notes": [],
    "specials": [],
    "state": {
      "_raw": ""
    }
  },
  {
    "damage": [
      12,
      28
    ],
    "framesOnBlock": {
      "_raw": "-16",
      "lower": "-16",
      "properties": []
    },
    "framesOnCounter": {
      "_raw": "",
      "lower": "",
      "properties": []
    },
    "framesOnHit": {
      "_raw": "+21a",
      "lower": "+21",
      "properties": [
        "a"
      ]
    },
    "framesOnStartup": {
      "_raw": ",i31~i32",
      "lower": "i31",
      "properties": [],
      "upper": "i32"
    },
    "hitLevels": [
      "l",
      "M"
    ],
    "index": 105,
    "input": "CD.DF+4,2",
    "name": "Depraved Savagery",
    "notes": [
      "Combo from 1st hit",
      "Chip damage on block"
    ],
    "specials": [
      "Balcony Break",
      "Spike"
    ],
    "state": {
      "_raw": ""
    }
  },
  {
    "damage": [],
    "framesOnBlock": {
      "_raw": "",
      "lower": "",
      "properties": []
    },
    "framesOnCounter": {
      "_raw": "",
      "lower": "",
      "properties": []
    },
    "framesOnHit": {
      "_raw": "",
      "lower": "",
      "properties": []
    },
    "framesOnStartup": {
      "_raw": "",
      "lower": "",
      "properties": []
    },
    "hitLevels": [],
    "index": 106,
    "input": "f+3+4",
    "name": "Zenshin",
    "notes": [
      "Enter Breaking Step r20 with DF",
      "Steps forward",
      "Actionable after 10f"
    ],
    "specials": [],
    "state": {
      "_raw": ""
    }
  },
  {
    "damage": [
      14
    ],
    "framesOnBlock": {
      "_raw": "-3",
      "lower": "-3",
      "properties": []
    },
    "framesOnCounter": {
      "_raw": "",
      "lower": "",
      "properties": []
    },
    "framesOnHit": {
      "_raw": "+8",
      "lower": "+8",
      "properties": []
    },
    "framesOnStartup": {
      "_raw": "i16~i17",
      "lower": "i16",
      "properties": [],
      "upper": "i17"
    },
    "hitLevels": [
      "m"
    ],
    "index": 108,
    "input": "ZEN.1",
    "name": "",
    "notes": [],
    "specials": [],
    "state": {
      "_raw": ""
    }
  },
  {
    "damage": [
      14,
      21
    ],
    "framesOnBlock": {
      "_raw": "-14",
      "lower": "-14",
      "properties": []
    },
    "framesOnCounter": {
      "_raw": "",
      "lower": "",
      "properties": []
    },
    "framesOnHit": {
      "_raw": "+32a (+6)",
      "lower": "+32",
      "properties": [
        "a"
      ],
      "tech": "+6"
    },
    "framesOnStartup": {
      "_raw": ",i23~24",
      "lower": "i23",
      "properties": [],
      "upper": "24"
    },
    "hitLevels": [
      "m",
      "m"
    ],
    "index": 109,
    "input": "ZEN.1,2",
    "name": "Brimstone Bite",
    "notes": [
      "Combo from 1st hit with 6f delay",
      "Input can be delayed 12f",
      "Move can be delayed 11f",
      "Cancel to Breaking Step -11 -12 r40 with DF on frame 20"
    ],
    "specials": [
      "Balcony Break"
    ],
    "state": {
      "_raw": ""
    }
  },
  {
    "damage": [
      14,
      14,
      14
    ],
    "framesOnBlock": {
      "_raw": "-9",
      "lower": "-9",
      "properties": []
    },
    "framesOnCounter": {
      "_raw": "",
      "lower": "",
      "properties": []
    },
    "framesOnHit": {
      "_raw": "+0d",
      "lower": "+0",
      "properties": [
        "d"
      ]
    },
    "framesOnStartup": {
      "_raw": ",i24~25",
      "lower": "i24",
      "properties": [],
      "upper": "25"
    },
    "hitLevels": [
      "m",
      "h",
      "t"
    ],
    "index": 110,
    "input": "ZEN.1,3",
    "name": "Kazama Style Leg Strike Flurry",
    "notes": [
      "Combo from 1st hit",
      "Transition to attack throw on standing or airborne hit",
      "+33a (+18) on side hit",
      "+18a (+11) and balcony break on BT hit"
    ],
    "specials": [],
    "state": {
      "_raw": ""
    }
  },
  {
    "damage": [
      20
    ],
    "framesOnBlock": {
      "_raw": "-9",
      "lower": "-9",
      "properties": []
    },
    "framesOnCounter": {
      "_raw": "+22a",
      "lower": "+22",
      "properties": [
        "a"
      ]
    },
    "framesOnHit": {
      "_raw": "+10g",
      "lower": "+10",
      "properties": [
        "g"
      ]
    },
    "framesOnStartup": {
      "_raw": "i17~i18",
      "lower": "i17",
      "properties": [],
      "upper": "i18"
    },
    "hitLevels": [
      "m"
    ],
    "index": 112,
    "input": "ZEN.3",
    "name": "Halberd Heel",
    "notes": [
      "+17a (+8) on BT hit"
    ],
    "specials": [
      "Homing",
      "Balcony Break"
    ],
    "state": {
      "_raw": ""
    }
  },
  {
    "damage": [
      24
    ],
    "framesOnBlock": {
      "_raw": "+2~+8",
      "lower": "+2",
      "properties": [],
      "upper": "+8"
    },
    "framesOnCounter": {
      "_raw": "",
      "lower": "",
      "properties": []
    },
    "framesOnHit": {
      "_raw": "+17d~+23d",
      "lower": "+17",
      "properties": [
        "d",
        "d"
      ],
      "upper": "+23"
    },
    "framesOnStartup": {
      "_raw": "i27~i33",
      "lower": "i27",
      "properties": [],
      "upper": "i33"
    },
    "hitLevels": [
      "M"
    ],
    "index": 113,
    "input": "ZEN.4",
    "name": "Corpse Crusher",
    "notes": [
      "Chip damage on block"
    ],
    "specials": [
      "Spike"
    ],
    "state": {
      "_raw": ""
    }
  },
  {
    "damage": [
      10,
      20
    ],
    "framesOnBlock": {
      "_raw": "-14",
      "lower": "-14",
      "properties": []
    },
    "framesOnCounter": {
      "_raw": "",
      "lower": "",
      "properties": []
    },
    "framesOnHit": {
      "_raw": "+4 +16w",
      "lower": "+4",
      "properties": []
    },
    "framesOnStartup": {
      "_raw": "i24 i61",
      "lower": "i24",
      "properties": []
    },
    "hitLevels": [
      "l",
      "t"
    ],
    "index": 114,
    "input": "ZEN.1+2",
    "name": "Low Chop > Karmic Epicenter",
    "notes": [
      "Transition to attack throw on standing hit",
      "Recover standing after throw"
    ],
    "specials": [
      "Wall Crush +16g on hit"
    ],
    "state": {
      "_raw": ""
    }
  },
  {
    "damage": [
      25
    ],
    "framesOnBlock": {
      "_raw": "+9g~+15g",
      "lower": "+9",
      "properties": [
        "g",
        "g"
      ],
      "upper": "+15"
    },
    "framesOnCounter": {
      "_raw": "",
      "lower": "",
      "properties": []
    },
    "framesOnHit": {
      "_raw": "+19a (+9) +15w",
      "lower": "+19",
      "properties": [
        "a"
      ],
      "tech": "+9"
    },
    "framesOnStartup": {
      "_raw": "i21~27",
      "lower": "i21",
      "properties": [],
      "upper": "27"
    },
    "hitLevels": [
      "h"
    ],
    "index": 115,
    "input": "ZEN.3+4",
    "name": "Black Wing Bolt",
    "notes": [
      "Enter Breaking Step +8 +18a (+8) r32 with DF on frame 40",
      "Chip damage on block"
    ],
    "specials": [
      "Wall Crush +15g~+21g on block",
      "Balcony Break"
    ],
    "state": {
      "_raw": ""
    }
  },
  {
    "damage": [
      20
    ],
    "framesOnBlock": {
      "_raw": "-16",
      "lower": "-16",
      "properties": []
    },
    "framesOnCounter": {
      "_raw": "",
      "lower": "",
      "properties": []
    },
    "framesOnHit": {
      "_raw": "+31a (+21)",
      "lower": "+31",
      "properties": [
        "a"
      ],
      "tech": "+21"
    },
    "framesOnStartup": {
      "_raw": "i14~i16",
      "lower": "i14",
      "properties": [],
      "upper": "i16"
    },
    "hitLevels": [
      "m"
    ],
    "index": 116,
    "input": "ZEN.u+1",
    "name": "Black Wing Rondo",
    "notes": [
      "Chip damage on block"
    ],
    "specials": [
      "Tornado"
    ],
    "state": {
      "_raw": ""
    }
  },
  {
    "damage": [
      55
    ],
    "framesOnBlock": {
      "_raw": "-15",
      "lower": "-15",
      "properties": []
    },
    "framesOnCounter": {
      "_raw": "",
      "lower": "",
      "properties": []
    },
    "framesOnHit": {
      "_raw": "+0d",
      "lower": "+0",
      "properties": [
        "d"
      ]
    },
    "framesOnStartup": {
      "_raw": "i20",
      "lower": "i20",
      "properties": []
    },
    "hitLevels": [
      "m",
      "t"
    ],
    "index": 117,
    "input": "R.df+1+2",
    "name": "Polar Demon Gouge",
    "notes": [
      "Damage increases with lower health, maximum 82",
      "Freezes match timer on activation and on hit",
      "Restores recoverable health on hit",
      "Transition to attack throw on hit",
      "Consumes Rage"
    ],
    "specials": [
      "Rage Art",
      "Removes Recoverable Health",
      "Reversal Break"
    ],
    "state": {
      "_raw": ""
    }
  },
  {
    "damage": [],
    "framesOnBlock": {
      "_raw": "",
      "lower": "",
      "properties": []
    },
    "framesOnCounter": {
      "_raw": "",
      "lower": "",
      "properties": []
    },
    "framesOnHit": {
      "_raw": "",
      "lower": "",
      "properties": []
    },
    "framesOnStartup": {
      "_raw": "",
      "lower": "",
      "properties": []
    },
    "hitLevels": [],
    "index": 118,
    "input": "1+3+4",
    "name": "\nState of Zanshin\nMental Alertness\n",
    "notes": [],
    "specials": [],
    "state": {
      "_raw": ""
    }
  },
  {
    "damage": [],
    "framesOnBlock": {
      "_raw": "",
      "lower": "",
      "properties": []
    },
    "framesOnCounter": {
      "_raw": "",
      "lower": "",
      "properties": []
    },
    "framesOnHit": {
      "_raw": "",
      "lower": "",
      "properties": []
    },
    "framesOnStartup": {
      "_raw": "",
      "lower": "",
      "properties": []
    },
    "hitLevels": [],
    "index": 119,
    "input": "1+2+3+4",
    "name": "\nKi Charge\nSupercharger\n",
    "notes": [
      "Can't block for 5 seconds",
      "CH state for 5 seconds"
    ],
    "specials": [],
    "state": {
      "_raw": ""
    }
  },
  {
    "damage": [],
    "framesOnBlock": {
      "_raw": "",
      "lower": "",
      "properties": []
    },
    "framesOnCounter": {
      "_raw": "",
      "lower": "",
      "properties": []
    },
    "framesOnHit": {
      "_raw": "",
      "lower": "",
      "properties": []
    },
    "framesOnStartup": {
      "_raw": "",
      "lower": "",
      "properties": []
    },
    "hitLevels": [],
    "index": 120,
    "input": "b+1+3",
    "name": "Parry",
    "notes": [
      "Strong parry: parries all highs or mids except throws, unblockables and charge moves",
      "r14 after parrying",
      "Plus frames after parrying depend on the recovery of the parried move"
    ],
    "specials": [],
    "state": {
      "_raw": ""
    }
  },
  {
    "damage": [
      24
    ],
    "framesOnBlock": {
      "_raw": "-13",
      "lower": "-13",
      "properties": []
    },
    "framesOnCounter": {
      "_raw": "",
      "lower": "",
      "properties": []
    },
    "framesOnHit": {
      "_raw": "-2 (-10)",
      "lower": "-2",
      "properties": [],
      "tech": "-10"
    },
    "framesOnStartup": {
      "_raw": "i19~20",
      "lower": "i19",
      "properties": [],
      "upper": "20"
    },
    "hitLevels": [
      "L"
    ],
    "index": 121,
    "input": "OTG.d+1+2",
    "name": "Black Out",
    "notes": [],
    "specials": [
      "Spike"
    ],
    "state": {
      "_raw": ""
    }
  },
  {
    "damage": [
      35
    ],
    "framesOnBlock": {
      "_raw": "+0",
      "lower": "+0",
      "properties": []
    },
    "framesOnCounter": {
      "_raw": "",
      "lower": "",
      "properties": []
    },
    "framesOnHit": {
      "_raw": "+2d",
      "lower": "+2",
      "properties": [
        "d"
      ]
    },
    "framesOnStartup": {
      "_raw": "i12~i14",
      "lower": "i12",
      "properties": [],
      "upper": "i14"
    },
    "hitLevels": [
      "t"
    ],
    "index": 122,
    "input": "1+3",
    "name": "Double Face Kick",
    "notes": [
      "Throw break 1 or 2",
      "Jin recovers BT on break"
    ],
    "specials": [
      "Homing"
    ],
    "state": {
      "_raw": ""
    }
  },
  {
    "damage": [
      35
    ],
    "framesOnBlock": {
      "_raw": "-3",
      "lower": "-3",
      "properties": []
    },
    "framesOnCounter": {
      "_raw": "",
      "lower": "",
      "properties": []
    },
    "framesOnHit": {
      "_raw": "+0d",
      "lower": "+0",
      "properties": [
        "d"
      ]
    },
    "framesOnStartup": {
      "_raw": "i12~i14",
      "lower": "i12",
      "properties": [],
      "upper": "i14"
    },
    "hitLevels": [
      "t"
    ],
    "index": 123,
    "input": "2+4",
    "name": "Over the Shoulder Reverse",
    "notes": [
      "Throw break 1 or 2",
      "Side switch on hit"
    ],
    "specials": [
      "Homing"
    ],
    "state": {
      "_raw": ""
    }
  },
  {
    "damage": [
      43
    ],
    "framesOnBlock": {
      "_raw": "-3",
      "lower": "-3",
      "properties": []
    },
    "framesOnCounter": {
      "_raw": "",
      "lower": "",
      "properties": []
    },
    "framesOnHit": {
      "_raw": "+0",
      "lower": "+0",
      "properties": []
    },
    "framesOnStartup": {
      "_raw": "",
      "lower": "",
      "properties": []
    },
    "hitLevels": [
      "t"
    ],
    "index": 124,
    "input": "Leftthrow",
    "name": "Shoulder Flip",
    "notes": [],
    "specials": [],
    "state": {
      "_raw": ""
    }
  },
  {
    "damage": [
      40
    ],
    "framesOnBlock": {
      "_raw": "-3",
      "lower": "-3",
      "properties": []
    },
    "framesOnCounter": {
      "_raw": "",
      "lower": "",
      "properties": []
    },
    "framesOnHit": {
      "_raw": "+0d",
      "lower": "+0",
      "properties": [
        "d"
      ]
    },
    "framesOnStartup": {
      "_raw": "",
      "lower": "",
      "properties": []
    },
    "hitLevels": [
      "t"
    ],
    "index": 125,
    "input": "Rightthrow",
    "name": "Over the Limit",
    "notes": [
      "Throw break 2",
      "Side switch on hit"
    ],
    "specials": [],
    "state": {
      "_raw": ""
    }
  },
  {
    "damage": [
      50
    ],
    "framesOnBlock": {
      "_raw": "",
      "lower": "",
      "properties": []
    },
    "framesOnCounter": {
      "_raw": "",
      "lower": "",
      "properties": []
    },
    "framesOnHit": {
      "_raw": "+1d",
      "lower": "+1",
      "properties": [
        "d"
      ]
    },
    "framesOnStartup": {
      "_raw": "",
      "lower": "",
      "properties": []
    },
    "hitLevels": [
      "t"
    ],
    "index": 126,
    "input": "Backthrow",
    "name": "Pivoting Hip Throw",
    "notes": [
      "Unbreakable",
      "Side switch on hit"
    ],
    "specials": [],
    "state": {
      "_raw": ""
    }
  },
  {
    "damage": [
      40
    ],
    "framesOnBlock": {
      "_raw": "-2",
      "lower": "-2",
      "properties": []
    },
    "framesOnCounter": {
      "_raw": "",
      "lower": "",
      "properties": []
    },
    "framesOnHit": {
      "_raw": "-4d",
      "lower": "-4",
      "properties": [
        "d"
      ]
    },
    "framesOnStartup": {
      "_raw": "i12",
      "lower": "i12",
      "properties": []
    },
    "hitLevels": [
      "t"
    ],
    "index": 127,
    "input": "df+2+3",
    "name": "Shun Ren Dan",
    "notes": [
      "Throw break 2"
    ],
    "specials": [],
    "state": {
      "_raw": ""
    }
  },
  {
    "damage": [
      40
    ],
    "framesOnBlock": {
      "_raw": "+0",
      "lower": "+0",
      "properties": []
    },
    "framesOnCounter": {
      "_raw": "",
      "lower": "",
      "properties": []
    },
    "framesOnHit": {
      "_raw": "+0d",
      "lower": "+0",
      "properties": [
        "d"
      ]
    },
    "framesOnStartup": {
      "_raw": "i12",
      "lower": "i12",
      "properties": []
    },
    "hitLevels": [
      "h"
    ],
    "index": 128,
    "input": "uf+1+2",
    "name": "Tidal Wave",
    "notes": [
      "Throw break 1+2"
    ],
    "specials": [
      "Floor Break"
    ],
    "state": {
      "_raw": ""
    }
  },
  {
    "damage": [
      40
    ],
    "framesOnBlock": {
      "_raw": "-2",
      "lower": "-2",
      "properties": []
    },
    "framesOnCounter": {
      "_raw": "",
      "lower": "",
      "properties": []
    },
    "framesOnHit": {
      "_raw": "0",
      "lower": "",
      "properties": []
    },
    "framesOnStartup": {
      "_raw": "i12",
      "lower": "i12",
      "properties": []
    },
    "hitLevels": [
      "h"
    ],
    "index": 129,
    "input": "qcb+1+3",
    "name": "Complicated Wire",
    "notes": [
      "Throw break 1",
      "Opponent recovers FUFA"
    ],
    "specials": [],
    "state": {
      "_raw": ""
    }
  }
]