[
  {
    "id": "Raven-1",
    "parent": null,
    "name": "Jab",
    "input": 1,
    "startup": "i10",
    "hitLevels": "h",
    "damage": 5,
    "onBlock": 1,
    "onHit": 8,
    "onCounterHit": null,
    "states": null,
    "index": null
  },
  {
    "id": "Raven-1+2",
    "parent": null,
    "name": "Crusader",
    "input": "1+2",
    "startup": "i14",
    "hitLevels": "m",
    "damage": 20,
    "onBlock": -9,
    "onHit": "+15a",
    "onCounterHit": null,
    "states": null,
    "index": null
  },
  {
    "id": "Raven-1,2",
    "parent": "Raven-1",
    "name": "Left Right Combo",
    "input": ",2",
    "startup": ",i12",
    "hitLevels": ",h",
    "damage": ",12",
    "onBlock": -3,
    "onHit": 7,
    "onCounterHit": null,
    "states": null,
    "index": 16
  },
  {
    "id": "Raven-1+2+3+4",
    "parent": null,
    "name": "Ki Charge",
    "input": "1+2+3+4",
    "startup": null,
    "hitLevels": null,
    "damage": null,
    "onBlock": null,
    "onHit": null,
    "onCounterHit": null,
    "states": null,
    "index": 68
  },
  {
    "id": "Raven-1+2+3+4,b,f,1+2",
    "parent": "Raven-1+2+3+4",
    "name": "Dead End",
    "input": ",b,f,1+2",
    "startup": ",i59~61",
    "hitLevels": ",m!",
    "damage": ",60",
    "onBlock": null,
    "onHit": "+21a (+11)",
    "onCounterHit": null,
    "states": ",cs12~42",
    "index": 69
  },
  {
    "id": "Raven-1,2,4",
    "parent": "Raven-1,2",
    "name": "Left Right Combo &gt; Black Hole",
    "input": ",4",
    "startup": ",i23~25",
    "hitLevels": ",m",
    "damage": ",20",
    "onBlock": "-14~-12",
    "onHit": "+15a (-2)",
    "onCounterHit": null,
    "states": ",js23~42 fs43~45",
    "index": 17
  },
  {
    "id": "Raven-1+3",
    "parent": null,
    "name": "Grave Digger",
    "input": "1+3",
    "startup": "i12~14",
    "hitLevels": "t",
    "damage": 35,
    "onBlock": -6,
    "onHit": "+0d",
    "onCounterHit": null,
    "states": null,
    "index": 115
  },
  {
    "id": "Raven-2",
    "parent": null,
    "name": "Right Jab",
    "input": 2,
    "startup": "i10",
    "hitLevels": "h",
    "damage": 9,
    "onBlock": -1,
    "onHit": 8,
    "onCounterHit": null,
    "states": null,
    "index": null
  },
  {
    "id": "Raven-2+3",
    "parent": null,
    "name": "Heat Burst",
    "input": "2+3",
    "startup": "i16",
    "hitLevels": "m",
    "damage": 12,
    "onBlock": 1,
    "onHit": "+2c",
    "onCounterHit": null,
    "states": "pc7~",
    "index": null
  },
  {
    "id": "Raven-2,3",
    "parent": "Raven-2",
    "name": "PDK Combo",
    "input": ",3",
    "startup": ",i22",
    "hitLevels": ",l",
    "damage": ",10",
    "onBlock": -13,
    "onHit": -2,
    "onCounterHit": null,
    "states": ",cs6~",
    "index": 18
  },
  {
    "id": "Raven-2+4",
    "parent": null,
    "name": "Salamander",
    "input": "2+4",
    "startup": "i12~14",
    "hitLevels": "t",
    "damage": 35,
    "onBlock": -3,
    "onHit": "+0d",
    "onCounterHit": null,
    "states": null,
    "index": 116
  },
  {
    "id": "Raven-2,4",
    "parent": "Raven-2",
    "name": "PK Combo",
    "input": ",4",
    "startup": ",i18~19",
    "hitLevels": ",h",
    "damage": ",16",
    "onBlock": "-8~-7",
    "onHit": 8,
    "onCounterHit": null,
    "states": null,
    "index": 19
  },
  {
    "id": "Raven-3",
    "parent": null,
    "name": null,
    "input": 3,
    "startup": ",i14~15",
    "hitLevels": "m",
    "damage": 10,
    "onBlock": "-8~-7",
    "onHit": "+3~+4",
    "onCounterHit": null,
    "states": null,
    "index": null
  },
  {
    "id": "Raven-3,3",
    "parent": "Raven-3",
    "name": null,
    "input": ",3",
    "startup": ",i17~18",
    "hitLevels": ",h",
    "damage": ",16",
    "onBlock": "-8~-7",
    "onHit": "+5~+6",
    "onCounterHit": null,
    "states": null,
    "index": null
  },
  {
    "id": "Raven-3,3,4",
    "parent": "Raven-3,3",
    "name": "Valkyrie Lance Combo",
    "input": ",4",
    "startup": ",i26~27",
    "hitLevels": ",h",
    "damage": ",20",
    "onBlock": -9,
    "onHit": "+39a (-19)",
    "onCounterHit": "+66a (+50)",
    "states": null,
    "index": 20
  },
  {
    "id": "Raven-3+4",
    "parent": null,
    "name": "Soulzone",
    "input": "3+4",
    "startup": null,
    "hitLevels": null,
    "damage": null,
    "onBlock": null,
    "onHit": null,
    "onCounterHit": null,
    "states": null,
    "index": null
  },
  {
    "id": "Raven-3~4",
    "parent": null,
    "name": "Chariot",
    "input": "3~4",
    "startup": "i25~26 i31~36",
    "hitLevels": "m,M",
    "damage": "10,16",
    "onBlock": "-9~-4",
    "onHit": "+19a",
    "onCounterHit": null,
    "states": null,
    "index": 22
  },
  {
    "id": "Raven-3~4,F",
    "parent": "Raven-3~4",
    "name": "Chariot to Blind Roll",
    "input": ",F",
    "startup": null,
    "hitLevels": null,
    "damage": null,
    "onBlock": "-39~-36",
    "onHit": -8,
    "onCounterHit": null,
    "states": ",js13~41 fs42~44",
    "index": null
  },
  {
    "id": "Raven-4",
    "parent": null,
    "name": "High Kick",
    "input": 4,
    "startup": "i12~13",
    "hitLevels": "h",
    "damage": 16,
    "onBlock": "-7~-6",
    "onHit": "+3~+4",
    "onCounterHit": null,
    "states": null,
    "index": null
  },
  {
    "id": "Raven-4,1",
    "parent": "Raven-4",
    "name": "Brocken Connect",
    "input": ",1",
    "startup": ",i19~20",
    "hitLevels": ",h",
    "damage": ",13",
    "onBlock": "-3~-2",
    "onHit": "+7~+8",
    "onCounterHit": null,
    "states": null,
    "index": 21
  },
  {
    "id": "Raven-4~3",
    "parent": null,
    "name": "Hydra Bite",
    "input": "4~3",
    "startup": "i16 i29~30",
    "hitLevels": "m,m",
    "damage": "8,10",
    "onBlock": "-16~-15",
    "onHit": "+31a (+21)",
    "onCounterHit": null,
    "states": "js14~27 fs28~30",
    "index": null
  },
  {
    "id": "Raven-4~3,1",
    "parent": "Raven-4~3",
    "name": "Hydra Bite Low",
    "input": ",1",
    "startup": ",i34~35",
    "hitLevels": ",l",
    "damage": ",15",
    "onBlock": "-13~-2",
    "onHit": "+4~+5",
    "onCounterHit": null,
    "states": ",cs1~",
    "index": 23
  },
  {
    "id": "Raven-4~3,3",
    "parent": "Raven-4~3",
    "name": "Hydra Bite High",
    "input": ",3",
    "startup": ",i24~27",
    "hitLevels": ",h",
    "damage": ",18",
    "onBlock": "-3~+0",
    "onHit": "+14a",
    "onCounterHit": null,
    "states": null,
    "index": 24
  },
  {
    "id": "Raven-4~3,4",
    "parent": "Raven-4~3",
    "name": "Hydra Bite Mid",
    "input": ",4",
    "startup": ",i33~34",
    "hitLevels": ",m",
    "damage": ",20",
    "onBlock": "-14~-13",
    "onHit": "+15a",
    "onCounterHit": null,
    "states": null,
    "index": 25
  },
  {
    "id": "Raven-b+1",
    "parent": null,
    "name": "Elbow Strike",
    "input": "b+1",
    "startup": "i16~17",
    "hitLevels": "h",
    "damage": 21,
    "onBlock": "+7c~+8c",
    "onHit": "+10c~+11c",
    "onCounterHit": null,
    "states": null,
    "index": 43
  },
  {
    "id": "Raven-b+1+2",
    "parent": null,
    "name": "Alternating Smash",
    "input": "b+1+2",
    "startup": "i28~30",
    "hitLevels": "m",
    "damage": 30,
    "onBlock": "-15~-13",
    "onHit": "+20a (+10)",
    "onCounterHit": null,
    "states": null,
    "index": 51
  },
  {
    "id": "Raven-b+1+3",
    "parent": null,
    "name": "Utsusemi Escape",
    "input": "b+1+3",
    "startup": null,
    "hitLevels": null,
    "damage": null,
    "onBlock": null,
    "onHit": null,
    "onCounterHit": null,
    "states": "ps1~10",
    "index": null
  },
  {
    "id": "Raven-b+1+3,P",
    "parent": "Raven-b+1+3",
    "name": "Utsusemi Escape",
    "input": ",P",
    "startup": null,
    "hitLevels": null,
    "damage": null,
    "onBlock": null,
    "onHit": -31,
    "onCounterHit": null,
    "states": "js1~32 cs33~",
    "index": null
  },
  {
    "id": "Raven-b+2",
    "parent": null,
    "name": null,
    "input": "b+2",
    "startup": "i15~17",
    "hitLevels": "h",
    "damage": 12,
    "onBlock": "-14~-12",
    "onHit": "-3~-1",
    "onCounterHit": null,
    "states": null,
    "index": null
  },
  {
    "id": "Raven-b+2,2",
    "parent": "Raven-b+2",
    "name": null,
    "input": ",2",
    "startup": ",i22",
    "hitLevels": ",m",
    "damage": ",17",
    "onBlock": -3,
    "onHit": 6,
    "onCounterHit": 8,
    "states": null,
    "index": null
  },
  {
    "id": "Raven-b+2,2,1+2",
    "parent": "Raven-b+2,2",
    "name": "Deadly Talon",
    "input": ",1+2",
    "startup": ",i20~21",
    "hitLevels": ",L",
    "damage": ",20",
    "onBlock": "-30~-29",
    "onHit": "+3d",
    "onCounterHit": null,
    "states": ",cs18~29",
    "index": 45
  },
  {
    "id": "Raven-b+2,2,3",
    "parent": "Raven-b+2,2",
    "name": "Unicorn&#039;s Tail",
    "input": ",3",
    "startup": "i21~22",
    "hitLevels": ",M",
    "damage": ",20",
    "onBlock": "-19~-18",
    "onHit": "+12a (-5)",
    "onCounterHit": "+26a (+16)",
    "states": null,
    "index": 44
  },
  {
    "id": "Raven-b+2,4",
    "parent": "Raven-b+2",
    "name": "Missing Worm",
    "input": ",4",
    "startup": ",i24~25",
    "hitLevels": ",h",
    "damage": ",13",
    "onBlock": "-7~-6",
    "onHit": "+4~+5",
    "onCounterHit": null,
    "states": null,
    "index": null
  },
  {
    "id": "Raven-b+2,4,2",
    "parent": "Raven-b+2,4",
    "name": "Missing Worm &gt; Phantom Halberd",
    "input": ",2",
    "startup": ",i19~20",
    "hitLevels": ",sm",
    "damage": ",21",
    "onBlock": -13,
    "onHit": "+24a (+9)",
    "onCounterHit": null,
    "states": null,
    "index": 46
  },
  {
    "id": "Raven-b+2,4,H.2",
    "parent": "Raven-b+2,4",
    "name": "Missing Worm &gt; Phantom Halberd",
    "input": ",H.2",
    "startup": "i19~20, i39~-41",
    "hitLevels": ",sm,sm",
    "damage": ",21,30",
    "onBlock": "-3~-1",
    "onHit": "+24a (+9)",
    "onCounterHit": null,
    "states": null,
    "index": null
  },
  {
    "id": "Raven-b+3",
    "parent": null,
    "name": "Hades Heel",
    "input": "b+3",
    "startup": "i27~29",
    "hitLevels": "M",
    "damage": 23,
    "onBlock": "+4~+6",
    "onHit": "+15a",
    "onCounterHit": null,
    "states": null,
    "index": 47
  },
  {
    "id": "Raven-b+3+4",
    "parent": null,
    "name": "Labyrinth",
    "input": "b+3+4",
    "startup": null,
    "hitLevels": null,
    "damage": null,
    "onBlock": null,
    "onHit": null,
    "onCounterHit": null,
    "states": null,
    "index": null
  },
  {
    "id": "Raven-b+4",
    "parent": null,
    "name": null,
    "input": "b+4",
    "startup": "i14~15",
    "hitLevels": "m",
    "damage": 13,
    "onBlock": "-9~-8",
    "onHit": "-1~+0",
    "onCounterHit": null,
    "states": null,
    "index": null
  },
  {
    "id": "Raven-b+4,4",
    "parent": "Raven-b+4",
    "name": "Skull Smasher",
    "input": ",4",
    "startup": ",i17~19",
    "hitLevels": ",m",
    "damage": ",20",
    "onBlock": "-8~-6",
    "onHit": "+6c~+8c",
    "onCounterHit": null,
    "states": null,
    "index": 48
  },
  {
    "id": "Raven-b+4,B+4",
    "parent": "Raven-b+4",
    "name": "Skull Smasher Feint",
    "input": ",B+4",
    "startup": ",i37~42",
    "hitLevels": ",M",
    "damage": ",24",
    "onBlock": "+1c~+6c",
    "onHit": "+2c~+7c",
    "onCounterHit": "+12a",
    "states": null,
    "index": 49
  },
  {
    "id": "Raven-b+4,B+4~3",
    "parent": "Raven-b+4,B+4",
    "name": "Skull Smasher Feint Low",
    "input": "~3",
    "startup": ",i20",
    "hitLevels": ",L",
    "damage": ",11",
    "onBlock": -11,
    "onHit": 0,
    "onCounterHit": null,
    "states": ",cs12~37",
    "index": null
  },
  {
    "id": "Raven-b+4,B+4~3,3+4",
    "parent": "Raven-b+4,B+4~3",
    "name": "Skull Spin",
    "input": ",3+4",
    "startup": ",i26~30",
    "hitLevels": ",m",
    "damage": ",15",
    "onBlock": "-25~-21",
    "onHit": "+6a",
    "onCounterHit": null,
    "states": null,
    "index": 50
  },
  {
    "id": "Raven-Back throw",
    "parent": null,
    "name": "Dark Matter",
    "input": "Back throw",
    "startup": null,
    "hitLevels": "t",
    "damage": 50,
    "onBlock": null,
    "onHit": "-4d",
    "onCounterHit": null,
    "states": null,
    "index": 119
  },
  {
    "id": "Raven-(Back to wall).b,​b,​UB",
    "parent": null,
    "name": "Wall Jump Attack",
    "input": "(Back to wall).b,​b,​UB",
    "startup": "i40~43",
    "hitLevels": "m",
    "damage": 21,
    "onBlock": "+6~+9",
    "onHit": "+28a (+19)",
    "onCounterHit": null,
    "states": "is8~13 js?~? fs?~?",
    "index": null
  },
  {
    "id": "Raven-b,B+2",
    "parent": null,
    "name": "War Hound",
    "input": "b,B+2",
    "startup": "i17~18 i30~31",
    "hitLevels": "m,h",
    "damage": "15,21",
    "onBlock": "-10~-9",
    "onHit": "+5~+6",
    "onCounterHit": null,
    "states": "ps1?~",
    "index": 65
  },
  {
    "id": "Raven-b,B+2,P",
    "parent": "Raven-b,B+2",
    "name": "Blind Ghost",
    "input": ",P",
    "startup": ",i15~25",
    "hitLevels": ",t",
    "damage": ",35",
    "onBlock": "-8~+2",
    "onHit": "+0d",
    "onCounterHit": null,
    "states": null,
    "index": null
  },
  {
    "id": "Raven-BT.1",
    "parent": null,
    "name": "Blind Axe",
    "input": "BT.1",
    "startup": "i8",
    "hitLevels": "h",
    "damage": 7,
    "onBlock": "-1~+0",
    "onHit": "+5~+6",
    "onCounterHit": null,
    "states": null,
    "index": null
  },
  {
    "id": "Raven-BT.1+2",
    "parent": null,
    "name": "Crusader",
    "input": "BT.1+2",
    "startup": "i15~16",
    "hitLevels": "m",
    "damage": 23,
    "onBlock": -13,
    "onHit": "+30a (+22)",
    "onCounterHit": null,
    "states": "pc6~",
    "index": null
  },
  {
    "id": "Raven-BT.1,4",
    "parent": "Raven-BT.1",
    "name": "Blind Lance",
    "input": ",4",
    "startup": ",i16~17",
    "hitLevels": ",h",
    "damage": ",23",
    "onBlock": "-8~-7",
    "onHit": "+40a (-18)",
    "onCounterHit": "+67a (+51)",
    "states": null,
    "index": 78
  },
  {
    "id": "Raven-BT.2",
    "parent": null,
    "name": "Backfist",
    "input": "BT.2",
    "startup": "i10",
    "hitLevels": "h",
    "damage": 9,
    "onBlock": 0,
    "onHit": 7,
    "onCounterHit": null,
    "states": null,
    "index": null
  },
  {
    "id": "Raven-BT.2,1",
    "parent": "Raven-BT.2",
    "name": "Backfist &gt; Straight",
    "input": ",1",
    "startup": ",i14",
    "hitLevels": ",h",
    "damage": ",10",
    "onBlock": -1,
    "onHit": 3,
    "onCounterHit": null,
    "states": null,
    "index": 79
  },
  {
    "id": "Raven-BT.2,2",
    "parent": "Raven-BT.2",
    "name": "Blinding Knife",
    "input": ",2",
    "startup": ",i21~22",
    "hitLevels": ",m",
    "damage": ",12",
    "onBlock": "-9~-8",
    "onHit": "+2~+3",
    "onCounterHit": null,
    "states": null,
    "index": null
  },
  {
    "id": "Raven-BT.2,2,1",
    "parent": "Raven-BT.2,2",
    "name": "Blinding Knife &gt; Phantom Javelin",
    "input": ",1",
    "startup": ",i18~19",
    "hitLevels": ",sm",
    "damage": ",21",
    "onBlock": -13,
    "onHit": "+2a (-7)",
    "onCounterHit": null,
    "states": null,
    "index": 80
  },
  {
    "id": "Raven-BT.2,2,H.1",
    "parent": "Raven-BT.2,2",
    "name": "Blinding Knife ＞ Phantom Javelin",
    "input": ",H.1",
    "startup": "i18~19, i39~47",
    "hitLevels": ",sm,sm",
    "damage": "21,30",
    "onBlock": -3,
    "onHit": "+2a (-7)",
    "onCounterHit": null,
    "states": null,
    "index": null
  },
  {
    "id": "Raven-BT.3",
    "parent": null,
    "name": null,
    "input": "BT.3",
    "startup": "i10",
    "hitLevels": "h",
    "damage": 10,
    "onBlock": -11,
    "onHit": 0,
    "onCounterHit": null,
    "states": null,
    "index": null
  },
  {
    "id": "Raven-BT.3+4",
    "parent": null,
    "name": "Spiral Cannon",
    "input": "BT.3+4",
    "startup": "i15 i34~35",
    "hitLevels": "m,m",
    "damage": "5,16",
    "onBlock": -14,
    "onHit": "+43a (+39)",
    "onCounterHit": null,
    "states": "js13~31 fs32~34",
    "index": 85
  },
  {
    "id": "Raven-BT.3,4",
    "parent": "Raven-BT.3",
    "name": null,
    "input": ",4",
    "startup": ",i28~30",
    "hitLevels": ",m",
    "damage": ",17",
    "onBlock": "+0~+2",
    "onHit": "+1~+3",
    "onCounterHit": "+11g~+13g",
    "states": null,
    "index": null
  },
  {
    "id": "Raven-BT.3,4,3",
    "parent": "Raven-BT.3,4",
    "name": "Crescent Mirage",
    "input": ",3",
    "startup": ",i27~30",
    "hitLevels": ",M",
    "damage": ",22",
    "onBlock": "-6~-3",
    "onHit": "+18a",
    "onCounterHit": null,
    "states": ",js1~27 fs28~30",
    "index": 81
  },
  {
    "id": "Raven-BT.3,4,4",
    "parent": "Raven-BT.3,4",
    "name": "Fafnir",
    "input": ",4",
    "startup": ",i32~34",
    "hitLevels": ",M",
    "damage": ",21",
    "onBlock": "-9~-8",
    "onHit": "+5a",
    "onCounterHit": null,
    "states": ",js12~31 fs32~34",
    "index": 82
  },
  {
    "id": "Raven-BT.3,4,4,F",
    "parent": "Raven-BT.3,4,4",
    "name": "Fafnir to Blind Roll",
    "input": ",F",
    "startup": null,
    "hitLevels": null,
    "damage": null,
    "onBlock": -36,
    "onHit": null,
    "onCounterHit": null,
    "states": ",js18~49 fs50~52",
    "index": null
  },
  {
    "id": "Raven-BT.4",
    "parent": null,
    "name": "Chronos Lathe",
    "input": "BT.4",
    "startup": "i19~20",
    "hitLevels": "m",
    "damage": 21,
    "onBlock": "-5~-4",
    "onHit": "+44a (-14)",
    "onCounterHit": null,
    "states": "js6~19",
    "index": 83
  },
  {
    "id": "Raven-BT.b+2",
    "parent": null,
    "name": null,
    "input": "BT.b+2",
    "startup": "i16~17",
    "hitLevels": "m",
    "damage": 14,
    "onBlock": "-2~-1",
    "onHit": "+6~+7",
    "onCounterHit": null,
    "states": null,
    "index": null
  },
  {
    "id": "Raven-BT.b+2,3",
    "parent": "Raven-BT.b+2",
    "name": "Abyss Cannon",
    "input": ",3",
    "startup": ",i20 i39~40",
    "hitLevels": ",m,m",
    "damage": ",5,16",
    "onBlock": -14,
    "onHit": "+42a (+38)",
    "onCounterHit": null,
    "states": ",js18~36 fs37~39",
    "index": 93
  },
  {
    "id": "Raven-BT.b+2,4",
    "parent": "Raven-BT.b+2",
    "name": "Abyss Spear",
    "input": ",4",
    "startup": ",i17~18",
    "hitLevels": ",h",
    "damage": ",13",
    "onBlock": 0,
    "onHit": 5,
    "onCounterHit": null,
    "states": null,
    "index": 94
  },
  {
    "id": "Raven-BT.b+3",
    "parent": null,
    "name": "Cannon Tail",
    "input": "BT.b+3",
    "startup": "i18~19",
    "hitLevels": "h",
    "damage": 22,
    "onBlock": "+4~+5",
    "onHit": "+41a",
    "onCounterHit": null,
    "states": null,
    "index": 95
  },
  {
    "id": "Raven-BT.b+3+4",
    "parent": null,
    "name": "Labyrinth to Front",
    "input": "BT.b+3+4",
    "startup": null,
    "hitLevels": null,
    "damage": null,
    "onBlock": null,
    "onHit": null,
    "onCounterHit": null,
    "states": null,
    "index": null
  },
  {
    "id": "Raven-BT.d+1",
    "parent": null,
    "name": "Crouch Spin Knuckle",
    "input": "BT.d+1",
    "startup": "i10",
    "hitLevels": "sl",
    "damage": 5,
    "onBlock": -3,
    "onHit": 6,
    "onCounterHit": null,
    "states": "cs1~",
    "index": null
  },
  {
    "id": "Raven-BT.d+2",
    "parent": null,
    "name": "Revenant Stab",
    "input": "BT.d+2",
    "startup": "i20",
    "hitLevels": "l",
    "damage": 20,
    "onBlock": -12,
    "onHit": 4,
    "onCounterHit": "+38d",
    "states": "cs1~",
    "index": null
  },
  {
    "id": "Raven-BT.d+3",
    "parent": null,
    "name": "Shinobi Cyclone",
    "input": "BT.d+3",
    "startup": "i25~27",
    "hitLevels": "L",
    "damage": 16,
    "onBlock": "-26~-24",
    "onHit": "+0~+2",
    "onCounterHit": null,
    "states": "cs4~48",
    "index": null
  },
  {
    "id": "Raven-BT.d+4",
    "parent": null,
    "name": "Crouch Spin Kick",
    "input": "BT.d+4",
    "startup": "i12",
    "hitLevels": "l",
    "damage": 6,
    "onBlock": -15,
    "onHit": -4,
    "onCounterHit": null,
    "states": "cs1~",
    "index": null
  },
  {
    "id": "Raven-BT.f+1",
    "parent": null,
    "name": "Soul Steal",
    "input": "BT.f+1",
    "startup": "I16",
    "hitLevels": "m",
    "damage": 18,
    "onBlock": -8,
    "onHit": 6,
    "onCounterHit": null,
    "states": null,
    "index": 86
  },
  {
    "id": "Raven-BT.f+1+2",
    "parent": null,
    "name": "Sixth Sense",
    "input": "BT.f+1+2",
    "startup": null,
    "hitLevels": null,
    "damage": null,
    "onBlock": null,
    "onHit": null,
    "onCounterHit": null,
    "states": "ps1~8",
    "index": null
  },
  {
    "id": "Raven-BT.f+1+2,P",
    "parent": "Raven-BT.f+1+2",
    "name": null,
    "input": ",P",
    "startup": null,
    "hitLevels": "t",
    "damage": 25,
    "onBlock": null,
    "onHit": "+5d",
    "onCounterHit": null,
    "states": null,
    "index": null
  },
  {
    "id": "Raven-BT.f+2",
    "parent": null,
    "name": null,
    "input": "BT.f+2",
    "startup": "i17~18",
    "hitLevels": "m",
    "damage": 13,
    "onBlock": "-5~-4",
    "onHit": "+6~+7",
    "onCounterHit": null,
    "states": null,
    "index": null
  },
  {
    "id": "Raven-BT.f+2,3",
    "parent": "Raven-BT.f+2",
    "name": "Cold Massacre",
    "input": ",3",
    "startup": ",i24~25",
    "hitLevels": ",M",
    "damage": ",15",
    "onBlock": "-7~-6",
    "onHit": "+14c~+15c",
    "onCounterHit": null,
    "states": null,
    "index": 87
  },
  {
    "id": "Raven-BT.f+2,4",
    "parent": "Raven-BT.f+2",
    "name": "Cold Worm",
    "input": ",4",
    "startup": ",i20~21",
    "hitLevels": ",h",
    "damage": ",17",
    "onBlock": "-7~-6",
    "onHit": "+4~+5",
    "onCounterHit": null,
    "states": null,
    "index": null
  },
  {
    "id": "Raven-BT.f+2,4,2",
    "parent": "Raven-BT.f+2,4",
    "name": "Cold Worm &gt; Phantom Halberd",
    "input": ",2",
    "startup": ",i19~20",
    "hitLevels": ",sm",
    "damage": ",21",
    "onBlock": -13,
    "onHit": "+24a (+9)",
    "onCounterHit": null,
    "states": null,
    "index": 88
  },
  {
    "id": "Raven-BT.f+3",
    "parent": null,
    "name": "Demon Knee",
    "input": "BT.f+3",
    "startup": "i13~14",
    "hitLevels": "m",
    "damage": 17,
    "onBlock": "-5~-4",
    "onHit": 6,
    "onCounterHit": "+38a (+30)",
    "states": null,
    "index": 89
  },
  {
    "id": "Raven-BT.f+3+4",
    "parent": null,
    "name": "Reverse Chakram",
    "input": "BT.f+3+4",
    "startup": "i25~27",
    "hitLevels": "M",
    "damage": 24,
    "onBlock": "-9~-7",
    "onHit": "+5a",
    "onCounterHit": null,
    "states": "js5~24 fs25~27 cs28~51",
    "index": 91
  },
  {
    "id": "Raven-BT.f+3+4,F",
    "parent": "Raven-BT.f+3+4",
    "name": "Reverse Chakram to Blind Roll",
    "input": ",F",
    "startup": null,
    "hitLevels": null,
    "damage": null,
    "onBlock": -36,
    "onHit": -22,
    "onCounterHit": null,
    "states": ",js18~49 fs50~52",
    "index": null
  },
  {
    "id": "Raven-BT.f+4",
    "parent": null,
    "name": "Kama Kick",
    "input": "BT.f+4",
    "startup": "i16",
    "hitLevels": "L",
    "damage": 13,
    "onBlock": -9,
    "onHit": 4,
    "onCounterHit": null,
    "states": null,
    "index": null
  },
  {
    "id": "Raven-BT.f+4,1",
    "parent": "Raven-BT.f+4",
    "name": "Trick Bang",
    "input": ",1",
    "startup": ",i22~23",
    "hitLevels": ",h",
    "damage": ",15",
    "onBlock": "-9~-8",
    "onHit": "+5~+6",
    "onCounterHit": null,
    "states": null,
    "index": 90
  },
  {
    "id": "Raven-BT.f,F+3",
    "parent": null,
    "name": "Gremlin Smasher",
    "input": "BT.f,F+3",
    "startup": "i21~22",
    "hitLevels": "m",
    "damage": 25,
    "onBlock": "-9~-8",
    "onHit": "+8a",
    "onCounterHit": null,
    "states": "cs4~22",
    "index": 97
  },
  {
    "id": "Raven-BT.f,F+3+4",
    "parent": null,
    "name": "Vermillion",
    "input": "BT.f,F+3+4",
    "startup": "i23~30",
    "hitLevels": "L",
    "damage": 17,
    "onBlock": "-18~-11",
    "onHit": "+24a",
    "onCounterHit": null,
    "states": "fs13~21 cs18~49",
    "index": 98
  },
  {
    "id": "Raven-BT.f,f,f",
    "parent": null,
    "name": "Blind Roll",
    "input": "BT.f,f,f",
    "startup": null,
    "hitLevels": null,
    "damage": null,
    "onBlock": null,
    "onHit": null,
    "onCounterHit": null,
    "states": "js10~41 fs42~44",
    "index": 99
  },
  {
    "id": "Raven-d+1",
    "parent": null,
    "name": "Crouch Jab",
    "input": "d+1",
    "startup": "i10",
    "hitLevels": "sl",
    "damage": 5,
    "onBlock": -5,
    "onHit": 6,
    "onCounterHit": null,
    "states": "cs4~",
    "index": null
  },
  {
    "id": "Raven-d+2",
    "parent": null,
    "name": "Crouch Straight",
    "input": "d+2",
    "startup": "i11",
    "hitLevels": "sl",
    "damage": 8,
    "onBlock": -4,
    "onHit": 7,
    "onCounterHit": null,
    "states": "cs4~",
    "index": null
  },
  {
    "id": "Raven-d+3",
    "parent": null,
    "name": "Stinging Low",
    "input": "d+3",
    "startup": "i15",
    "hitLevels": "L",
    "damage": 10,
    "onBlock": -11,
    "onHit": 0,
    "onCounterHit": null,
    "states": null,
    "index": 38
  },
  {
    "id": "Raven-d+4",
    "parent": null,
    "name": "Basilisk Fang",
    "input": "d+4",
    "startup": "i21",
    "hitLevels": "L",
    "damage": 18,
    "onBlock": -13,
    "onHit": -2,
    "onCounterHit": "+13g",
    "states": "cs6~",
    "index": 39
  },
  {
    "id": "Raven-db+2",
    "parent": null,
    "name": "Assassin&#039;s Sting",
    "input": "db+2",
    "startup": "i13~14",
    "hitLevels": "m",
    "damage": 13,
    "onBlock": "-4~-3",
    "onHit": "+5~+6",
    "onCounterHit": null,
    "states": null,
    "index": null
  },
  {
    "id": "Raven-db+2,1",
    "parent": "Raven-db+2",
    "name": "Assassin&#039;s Sting Combo",
    "input": ",1",
    "startup": ",i22~23",
    "hitLevels": ",h",
    "damage": ",15",
    "onBlock": "-1~+0",
    "onHit": "+8~+9",
    "onCounterHit": null,
    "states": null,
    "index": null
  },
  {
    "id": "Raven-db+2,1,1",
    "parent": "Raven-db+2,1",
    "name": "Assassin&#039;s Sting &gt; Phantom Javelin",
    "input": ",1",
    "startup": ",i18~19",
    "hitLevels": ",sm",
    "damage": ",21",
    "onBlock": -13,
    "onHit": "+2a (-7)",
    "onCounterHit": null,
    "states": null,
    "index": 40
  },
  {
    "id": "Raven-db+2,1,H.1",
    "parent": "Raven-db+2,1",
    "name": "Assassin&#039;s Sting &gt; Phantom Javelin",
    "input": ",H.1",
    "startup": "i18~19, i39~47",
    "hitLevels": ",sm,sm",
    "damage": ",21,30",
    "onBlock": "-3~+5",
    "onHit": "+2a (-7)",
    "onCounterHit": null,
    "states": null,
    "index": null
  },
  {
    "id": "Raven-db+3",
    "parent": null,
    "name": "Killer Bee",
    "input": "db+3",
    "startup": "i28~29",
    "hitLevels": "L",
    "damage": 19,
    "onBlock": "-12~-11",
    "onHit": "+5~+6",
    "onCounterHit": "+39d",
    "states": "js8~24 fs25~27 cs28~",
    "index": 41
  },
  {
    "id": "Raven-db+4",
    "parent": null,
    "name": "Shinobi Cyclone",
    "input": "db+4",
    "startup": "i24~25",
    "hitLevels": "L",
    "damage": 21,
    "onBlock": "-14~-13",
    "onHit": "+4c~+5c",
    "onCounterHit": "+37a",
    "states": "cs6~49",
    "index": null
  },
  {
    "id": "Raven-df+1",
    "parent": null,
    "name": "Body Blow",
    "input": "df+1",
    "startup": "i14~15",
    "hitLevels": "m",
    "damage": 13,
    "onBlock": "-2~-1",
    "onHit": "+8~+9",
    "onCounterHit": null,
    "states": null,
    "index": null
  },
  {
    "id": "Raven-df+1+4",
    "parent": null,
    "name": "Orbiting Moon",
    "input": "df+1+4",
    "startup": "i11",
    "hitLevels": "t",
    "damage": 35,
    "onBlock": -2,
    "onHit": "+0d",
    "onCounterHit": null,
    "states": null,
    "index": 120
  },
  {
    "id": "Raven-df+1,4",
    "parent": "Raven-df+1",
    "name": "Body Blow &gt; Phantom Mace",
    "input": ",4",
    "startup": ",i18~27",
    "hitLevels": ",sm",
    "damage": ",25",
    "onBlock": -13,
    "onHit": "+32a (-26)",
    "onCounterHit": null,
    "states": null,
    "index": 32
  },
  {
    "id": "Raven-df+1,H.4",
    "parent": "Raven-df+1",
    "name": "Body Blow &gt; Phantom Mace",
    "input": ",H.4",
    "startup": "i18~27, i44~45",
    "hitLevels": ",sm,sm",
    "damage": ",25,30",
    "onBlock": "-3~-2",
    "onHit": "+32a (-26)",
    "onCounterHit": null,
    "states": null,
    "index": null
  },
  {
    "id": "Raven-df+2",
    "parent": null,
    "name": "Uppercut",
    "input": "df+2",
    "startup": "i16~18",
    "hitLevels": "m",
    "damage": 15,
    "onBlock": "-13~-11",
    "onHit": "+30a (+20)",
    "onCounterHit": null,
    "states": null,
    "index": null
  },
  {
    "id": "Raven-df+2,3",
    "parent": "Raven-df+2",
    "name": "Meat Hook",
    "input": ",3",
    "startup": ",i12~13",
    "hitLevels": ",h",
    "damage": ",17",
    "onBlock": "-8~-7",
    "onHit": "+28a (+19)",
    "onCounterHit": null,
    "states": null,
    "index": 33
  },
  {
    "id": "Raven-df+2,4",
    "parent": "Raven-df+2",
    "name": "Bolt Stunner",
    "input": ",4",
    "startup": ",i12~13",
    "hitLevels": ",m",
    "damage": ",24",
    "onBlock": "-15~-14",
    "onHit": "+11a (+2)",
    "onCounterHit": null,
    "states": null,
    "index": 34
  },
  {
    "id": "Raven-df+3",
    "parent": null,
    "name": "Shadow Snap Kick",
    "input": "df+3",
    "startup": "i16~17",
    "hitLevels": "h",
    "damage": 17,
    "onBlock": "-9~-8",
    "onHit": "+12a",
    "onCounterHit": "+46a (+36)",
    "states": "cs6~17",
    "index": null
  },
  {
    "id": "Raven-df+3+4",
    "parent": null,
    "name": "Crouch Step",
    "input": "df+3+4",
    "startup": null,
    "hitLevels": null,
    "damage": null,
    "onBlock": null,
    "onHit": null,
    "onCounterHit": null,
    "states": "cs",
    "index": null
  },
  {
    "id": "Raven-df+4",
    "parent": null,
    "name": null,
    "input": "df+4",
    "startup": "i15~16",
    "hitLevels": "m",
    "damage": 15,
    "onBlock": "-9~-8",
    "onHit": "+2~+3",
    "onCounterHit": null,
    "states": null,
    "index": null
  },
  {
    "id": "Raven-df+4,4",
    "parent": "Raven-df+4",
    "name": "Pendulum Kick",
    "input": ",4",
    "startup": ",i22~25",
    "hitLevels": ",M",
    "damage": ",16",
    "onBlock": "-14~-13",
    "onHit": "+6a",
    "onCounterHit": null,
    "states": null,
    "index": 36
  },
  {
    "id": "Raven-df+4,4,3",
    "parent": "Raven-df+4,4",
    "name": "Pendulum Shadow",
    "input": ",3",
    "startup": ",i27~30",
    "hitLevels": ",M",
    "damage": ",22",
    "onBlock": "-6~-3",
    "onHit": "+18a",
    "onCounterHit": null,
    "states": ",js1~27 fs28~30",
    "index": 37
  },
  {
    "id": "Raven-f+1+2",
    "parent": null,
    "name": "Minos Typhoon",
    "input": "f+1+2",
    "startup": "i18~19, i26",
    "hitLevels": "h,m",
    "damage": "10,20",
    "onBlock": -13,
    "onHit": "+30a (+4)",
    "onCounterHit": null,
    "states": "pc7~",
    "index": 31
  },
  {
    "id": "Raven-f+2",
    "parent": null,
    "name": null,
    "input": "f+2",
    "startup": "i15~16",
    "hitLevels": "m",
    "damage": 10,
    "onBlock": "-12~-11",
    "onHit": "-1~+0",
    "onCounterHit": null,
    "states": null,
    "index": null
  },
  {
    "id": "Raven-f+2,3",
    "parent": "Raven-f+2",
    "name": "Tartaros",
    "input": ",3",
    "startup": ",i21~22",
    "hitLevels": ",M",
    "damage": ",13",
    "onBlock": "-9~-8",
    "onHit": "+6c~+7c",
    "onCounterHit": null,
    "states": null,
    "index": 28
  },
  {
    "id": "Raven-f+3",
    "parent": null,
    "name": null,
    "input": "f+3",
    "startup": "i17",
    "hitLevels": "m",
    "damage": 18,
    "onBlock": -9,
    "onHit": 3,
    "onCounterHit": null,
    "states": null,
    "index": null
  },
  {
    "id": "Raven-f+3,2",
    "parent": "Raven-f+3",
    "name": "Circling Winds",
    "input": ",2",
    "startup": ",i30",
    "hitLevels": ",m",
    "damage": ",21",
    "onBlock": -14,
    "onHit": "+10a (+1)",
    "onCounterHit": "+30a (+22)",
    "states": null,
    "index": 29
  },
  {
    "id": "Raven-f+4",
    "parent": null,
    "name": "Lance Kick",
    "input": "f+4",
    "startup": "i15~16",
    "hitLevels": "h",
    "damage": 17,
    "onBlock": -12,
    "onHit": "+67a (+51)",
    "onCounterHit": null,
    "states": null,
    "index": 30
  },
  {
    "id": "Raven-FC.1",
    "parent": null,
    "name": "Crouch Jab",
    "input": "FC.1",
    "startup": "i10",
    "hitLevels": "sl",
    "damage": 5,
    "onBlock": -5,
    "onHit": 6,
    "onCounterHit": null,
    "states": "cs1~",
    "index": null
  },
  {
    "id": "Raven-FC.2",
    "parent": null,
    "name": "Crouch Straight",
    "input": "FC.2",
    "startup": "i11",
    "hitLevels": "sl",
    "damage": 8,
    "onBlock": -4,
    "onHit": 7,
    "onCounterHit": null,
    "states": "cs1~",
    "index": null
  },
  {
    "id": "Raven-FC.3",
    "parent": null,
    "name": "Crouch Spin Kick",
    "input": "FC.3",
    "startup": "i16",
    "hitLevels": "L",
    "damage": 10,
    "onBlock": -17,
    "onHit": -6,
    "onCounterHit": null,
    "states": "cs1~",
    "index": null
  },
  {
    "id": "Raven-FC.4",
    "parent": null,
    "name": "Crouch Chin Kick",
    "input": "FC.4",
    "startup": "i12",
    "hitLevels": "l",
    "damage": 6,
    "onBlock": -15,
    "onHit": -4,
    "onCounterHit": null,
    "states": "cs1~",
    "index": null
  },
  {
    "id": "Raven-FC.df+3",
    "parent": null,
    "name": "Aqua Spider",
    "input": "FC.df+3",
    "startup": "i20~22",
    "hitLevels": "L",
    "damage": 17,
    "onBlock": "-9~-7",
    "onHit": "+2~+4",
    "onCounterHit": "+30d",
    "states": "cs1~35",
    "index": 75
  },
  {
    "id": "Raven-FC.df+3+4",
    "parent": null,
    "name": "Tornado Destruction",
    "input": "FC.df+3+4",
    "startup": "i18~20 i34~36",
    "hitLevels": "L,sm",
    "damage": "17,25",
    "onBlock": "-23~-21",
    "onHit": "-5a",
    "onCounterHit": null,
    "states": "cs1~17",
    "index": 76
  },
  {
    "id": "Raven-FC.df,d,DF",
    "parent": null,
    "name": "Crouch Step",
    "input": "FC.df,d,DF",
    "startup": null,
    "hitLevels": null,
    "damage": null,
    "onBlock": null,
    "onHit": null,
    "onCounterHit": null,
    "states": "cs1~30",
    "index": 77
  },
  {
    "id": "Raven-FC.df,d,df,f",
    "parent": "Raven-FC.df,d,DF",
    "name": "Crouch Step to Shadow Sprint",
    "input": ",f",
    "startup": null,
    "hitLevels": null,
    "damage": null,
    "onBlock": null,
    "onHit": null,
    "onCounterHit": null,
    "states": null,
    "index": null
  },
  {
    "id": "Raven-f,F+2",
    "parent": null,
    "name": "Shadow Spear",
    "input": "f,F+2",
    "startup": "i15~16",
    "hitLevels": "m",
    "damage": 26,
    "onBlock": "-12~-11",
    "onHit": "+15a (+5)",
    "onCounterHit": null,
    "states": null,
    "index": 61
  },
  {
    "id": "Raven-f,F+3",
    "parent": null,
    "name": "Sudden Strike",
    "input": "f,F+3",
    "startup": "i15~18",
    "hitLevels": "m",
    "damage": 20,
    "onBlock": "-14~-11",
    "onHit": "+43a (+29)",
    "onCounterHit": null,
    "states": "js7~23 fs24~26",
    "index": 62
  },
  {
    "id": "Raven-f,F+4",
    "parent": null,
    "name": "Iron Maul",
    "input": "f,F+4",
    "startup": "i15~17",
    "hitLevels": "m",
    "damage": 21,
    "onBlock": "-10~-8",
    "onHit": "+21a (+4)",
    "onCounterHit": null,
    "states": null,
    "index": 63
  },
  {
    "id": "Raven-f,f,F+3",
    "parent": null,
    "name": "Typhon Fang",
    "input": "f,f,F+3",
    "startup": "i22~24",
    "hitLevels": "m",
    "damage": 20,
    "onBlock": "+4~+6",
    "onHit": "+6a",
    "onCounterHit": null,
    "states": "js14~34 fs35~37",
    "index": 64
  },
  {
    "id": "Raven-f,f,F+3,H.4",
    "parent": "Raven-f,f,F+3",
    "name": "Typhon Fang Phantom",
    "input": ",H.4",
    "startup": "i43~44",
    "hitLevels": ",sm",
    "damage": ",20",
    "onBlock": "+7~+8",
    "onHit": "+72a (+56)",
    "onCounterHit": null,
    "states": null,
    "index": null
  },
  {
    "id": "Raven-H.2+3",
    "parent": null,
    "name": "Pandemonium",
    "input": "H.2+3",
    "startup": "i18~20",
    "hitLevels": "m,t",
    "damage": "20,35",
    "onBlock": "+14g",
    "onHit": "+3a",
    "onCounterHit": null,
    "states": null,
    "index": null
  },
  {
    "id": "Raven-H.BT.f+2,4,2",
    "parent": "Raven-BT.f+2,4",
    "name": "Cold Worm &gt; Phantom Halberd",
    "input": ",H.2",
    "startup": "i19~20 i39~41",
    "hitLevels": ",sm,sm",
    "damage": ",21,30",
    "onBlock": "-3~-1",
    "onHit": "+24a (+9)",
    "onCounterHit": null,
    "states": null,
    "index": null
  },
  {
    "id": "Raven-Left throw",
    "parent": null,
    "name": "Neck Ringer",
    "input": "Left throw",
    "startup": null,
    "hitLevels": "t",
    "damage": 40,
    "onBlock": -3,
    "onHit": "-3d",
    "onCounterHit": null,
    "states": null,
    "index": 117
  },
  {
    "id": "Raven-qcf",
    "parent": null,
    "name": "Shadow Sprint",
    "input": "qcf",
    "startup": null,
    "hitLevels": null,
    "damage": null,
    "onBlock": null,
    "onHit": null,
    "onCounterHit": null,
    "states": null,
    "index": 100
  },
  {
    "id": "Raven-qcf+1",
    "parent": null,
    "name": "Fatal Elbow",
    "input": "qcf+1",
    "startup": "i16",
    "hitLevels": "m",
    "damage": 15,
    "onBlock": -9,
    "onHit": 4,
    "onCounterHit": "+15a",
    "states": null,
    "index": null
  },
  {
    "id": "Raven-qcf+1+2",
    "parent": null,
    "name": "Hellhound",
    "input": "qcf+1+2",
    "startup": "i24 i35",
    "hitLevels": "m,m",
    "damage": "10,20",
    "onBlock": 5,
    "onHit": "+11a (+2)",
    "onCounterHit": null,
    "states": null,
    "index": 106
  },
  {
    "id": "Raven-qcf+1,2",
    "parent": "Raven-qcf+1",
    "name": "Fatal Elbow &gt; Phantom Halberd",
    "input": ",2",
    "startup": ",i19~20",
    "hitLevels": ",sm",
    "damage": ",21",
    "onBlock": -13,
    "onHit": "+24a (+9)",
    "onCounterHit": null,
    "states": null,
    "index": 101
  },
  {
    "id": "Raven-qcf+1+2,P",
    "parent": "Raven-qcf+1+2",
    "name": "Blind Ghost",
    "input": ",P",
    "startup": ",i15~25",
    "hitLevels": ",t",
    "damage": ",35",
    "onBlock": "-8~+2",
    "onHit": "+0d",
    "onCounterHit": null,
    "states": null,
    "index": null
  },
  {
    "id": "Raven-qcf+1,H.2",
    "parent": "Raven-qcf+1",
    "name": "Fatal Elbow &gt; Phantom Halberd",
    "input": ",H.2",
    "startup": ",19~20, 39~41",
    "hitLevels": ",sm,sm",
    "damage": ",21,30",
    "onBlock": "-3~-1",
    "onHit": "+24a (+9)",
    "onCounterHit": null,
    "states": null,
    "index": null
  },
  {
    "id": "Raven-qcf+2",
    "parent": null,
    "name": "Buzzsaw",
    "input": "qcf+2",
    "startup": "i22~23",
    "hitLevels": "L",
    "damage": 18,
    "onBlock": "-12~-11",
    "onHit": "+5~+6",
    "onCounterHit": "+14~+15",
    "states": "cs10~45",
    "index": 102
  },
  {
    "id": "Raven-qcf+2~1",
    "parent": null,
    "name": "Laevateinn",
    "input": "qcf+2~1",
    "startup": "i20~21",
    "hitLevels": "m",
    "damage": 25,
    "onBlock": "-9~-8",
    "onHit": "+24a (+14)",
    "onCounterHit": null,
    "states": null,
    "index": 103
  },
  {
    "id": "Raven-qcf+3",
    "parent": null,
    "name": "Poison Needle &gt; Nightmare",
    "input": "qcf+3",
    "startup": "i16~17",
    "hitLevels": "h,t",
    "damage": "16,14",
    "onBlock": "-7~-6",
    "onHit": "-4d",
    "onCounterHit": null,
    "states": null,
    "index": 104
  },
  {
    "id": "Raven-qcf+4",
    "parent": null,
    "name": "Black Hole",
    "input": "qcf+4",
    "startup": "i18~20",
    "hitLevels": "M",
    "damage": 15,
    "onBlock": "-14~-12",
    "onHit": "+32a (+22)",
    "onCounterHit": null,
    "states": "fs20~32",
    "index": 105
  },
  {
    "id": "Raven-R.df+1+2",
    "parent": null,
    "name": "Wild Hunt X-ecutor",
    "input": "R.df+1+2",
    "startup": "i20",
    "hitLevels": "m,t",
    "damage": "55+",
    "onBlock": -15,
    "onHit": "+0d",
    "onCounterHit": null,
    "states": "pc8~",
    "index": null
  },
  {
    "id": "Raven-Right throw",
    "parent": null,
    "name": "Swift Assassin",
    "input": "Right throw",
    "startup": null,
    "hitLevels": "t",
    "damage": 40,
    "onBlock": -3,
    "onHit": "-4d",
    "onCounterHit": null,
    "states": null,
    "index": 118
  },
  {
    "id": "Raven-SZN.1",
    "parent": null,
    "name": "Swift Blade",
    "input": "SZN.1",
    "startup": "i14~15",
    "hitLevels": "h",
    "damage": 12,
    "onBlock": 1,
    "onHit": "+8~+9",
    "onCounterHit": null,
    "states": null,
    "index": null
  },
  {
    "id": "Raven-SZN.1+2",
    "parent": null,
    "name": "Oceanus Fissure",
    "input": "SZN.1+2",
    "startup": "i15~16",
    "hitLevels": "h",
    "damage": 25,
    "onBlock": "+0~+1",
    "onHit": "+23a",
    "onCounterHit": null,
    "states": null,
    "index": 112
  },
  {
    "id": "Raven-SZN.1,4",
    "parent": "Raven-SZN.1",
    "name": "Swift Blade &gt; Phantom Mace",
    "input": ",4",
    "startup": ",i18~27",
    "hitLevels": ",sm",
    "damage": ",25",
    "onBlock": -13,
    "onHit": "+32a (-26)",
    "onCounterHit": null,
    "states": null,
    "index": 108
  },
  {
    "id": "Raven-SZN.1,H.4",
    "parent": "Raven-SZN.1",
    "name": "Swift Blade &gt; Phantom Mace",
    "input": ",H.4",
    "startup": "i18~27, i44~45",
    "hitLevels": ",sm,sm",
    "damage": ",25,30",
    "onBlock": "-3~-2",
    "onHit": "+32a (-26)",
    "onCounterHit": null,
    "states": null,
    "index": null
  },
  {
    "id": "Raven-SZN.2",
    "parent": null,
    "name": "Dual Thanatos",
    "input": "SZN.2",
    "startup": "i18, i23~24",
    "hitLevels": "m,sm",
    "damage": "20,10",
    "onBlock": -9,
    "onHit": "+7a (-2)",
    "onCounterHit": null,
    "states": null,
    "index": 109
  },
  {
    "id": "Raven-SZN.3",
    "parent": null,
    "name": "Radius Flail",
    "input": "SZN.3",
    "startup": "i16~17",
    "hitLevels": "m",
    "damage": 16,
    "onBlock": -1,
    "onHit": "+5~+6",
    "onCounterHit": null,
    "states": "js9~17",
    "index": null
  },
  {
    "id": "Raven-SZN.3,2",
    "parent": "Raven-SZN.3",
    "name": "Radius Flail &gt; Phantom Halberd",
    "input": ",2",
    "startup": ",i19~20",
    "hitLevels": ",sm",
    "damage": ",21",
    "onBlock": -13,
    "onHit": "+24a (+9)",
    "onCounterHit": null,
    "states": null,
    "index": 110
  },
  {
    "id": "Raven-SZN.3,H.2",
    "parent": "Raven-SZN.3",
    "name": "Radius Flail &gt; Phantom Halberd",
    "input": ",H.2",
    "startup": "i19~20 i39~-41",
    "hitLevels": ",sm,sm",
    "damage": ",21,30",
    "onBlock": "-3~-1",
    "onHit": "+24a (+9)",
    "onCounterHit": null,
    "states": null,
    "index": null
  },
  {
    "id": "Raven-SZN.4",
    "parent": null,
    "name": "Cocytus Glide",
    "input": "SZN.4",
    "startup": "i17~24",
    "hitLevels": "L",
    "damage": 21,
    "onBlock": -14,
    "onHit": 4,
    "onCounterHit": "+13a",
    "states": "cs6~",
    "index": 111
  },
  {
    "id": "Raven-SZN.B",
    "parent": null,
    "name": "Blind Labyrinth",
    "input": "SZN.B",
    "startup": null,
    "hitLevels": null,
    "damage": null,
    "onBlock": null,
    "onHit": null,
    "onCounterHit": null,
    "states": "js1~17 fs15~17",
    "index": 114
  },
  {
    "id": "Raven-SZN.D",
    "parent": null,
    "name": "Blind Fall to Crouching State",
    "input": "SZN.D",
    "startup": null,
    "hitLevels": null,
    "damage": null,
    "onBlock": null,
    "onHit": null,
    "onCounterHit": null,
    "states": "js1~17 fs15~17",
    "index": null
  },
  {
    "id": "Raven-SZN.U",
    "parent": null,
    "name": "Blind Fall",
    "input": "SZN.U",
    "startup": null,
    "hitLevels": null,
    "damage": null,
    "onBlock": null,
    "onHit": null,
    "onCounterHit": null,
    "states": "js1~17 fs15~17",
    "index": 113
  },
  {
    "id": "Raven-u+3",
    "parent": null,
    "name": "Deathbringer",
    "input": "u+3",
    "startup": "i27~28",
    "hitLevels": "h",
    "damage": 23,
    "onBlock": 2,
    "onHit": "+6~+7",
    "onCounterHit": null,
    "states": "js9~30 fs31~33",
    "index": null
  },
  {
    "id": "Raven-u+3,3",
    "parent": "Raven-u+3",
    "name": "Deathbringer Low",
    "input": ",3",
    "startup": "i31~32",
    "hitLevels": ",L",
    "damage": ",18",
    "onBlock": "-16~-15",
    "onHit": "+16a",
    "onCounterHit": null,
    "states": ",cs14~39",
    "index": 54
  },
  {
    "id": "Raven-u+3,3,3",
    "parent": "Raven-u+3,3",
    "name": "Deathbringer Low &gt; Shadow",
    "input": ",3",
    "startup": ",i27~30",
    "hitLevels": ",M",
    "damage": ",22",
    "onBlock": "-6~-4",
    "onHit": "+18a",
    "onCounterHit": null,
    "states": ",js1~27 fs28~30",
    "index": 55
  },
  {
    "id": "Raven-ub+1",
    "parent": null,
    "name": null,
    "input": "ub+1",
    "startup": "i16",
    "hitLevels": "m",
    "damage": 11,
    "onBlock": -6,
    "onHit": 5,
    "onCounterHit": null,
    "states": null,
    "index": null
  },
  {
    "id": "Raven-ub+1,2",
    "parent": "Raven-ub+1",
    "name": "Gate Keeper",
    "input": ",2",
    "startup": ",i18~19",
    "hitLevels": ",m",
    "damage": ",13",
    "onBlock": "-13~-12",
    "onHit": "-2c~-1c",
    "onCounterHit": null,
    "states": null,
    "index": 53
  },
  {
    "id": "Raven-UB,b",
    "parent": null,
    "name": "Back Handspring",
    "input": "UB,b",
    "startup": null,
    "hitLevels": null,
    "damage": null,
    "onBlock": null,
    "onHit": null,
    "onCounterHit": null,
    "states": "js10~41 fs42~44",
    "index": null
  },
  {
    "id": "Raven-UB,b,3+4",
    "parent": "Raven-UB,b",
    "name": "Pandora Spin",
    "input": ",3+4",
    "startup": ",i38~40 i46~49 i51~54",
    "hitLevels": ",M!,M!,M!",
    "damage": ",20,20,20",
    "onBlock": null,
    "onHit": "-19a",
    "onCounterHit": null,
    "states": ",js21~56",
    "index": 67
  },
  {
    "id": "Raven-uf+1+2",
    "parent": null,
    "name": "Undertaker",
    "input": "uf+1+2",
    "startup": "i12",
    "hitLevels": "t",
    "damage": 40,
    "onBlock": -2,
    "onHit": "+0d",
    "onCounterHit": null,
    "states": null,
    "index": 121
  },
  {
    "id": "Raven-uf+3",
    "parent": null,
    "name": "Shadow Scythe",
    "input": "uf+3",
    "startup": "i29~30",
    "hitLevels": "M",
    "damage": 20,
    "onBlock": -9,
    "onHit": "+20a",
    "onCounterHit": null,
    "states": "js9~30",
    "index": 56
  },
  {
    "id": "Raven-uf+3+4",
    "parent": null,
    "name": null,
    "input": "uf+3+4",
    "startup": "i23~25",
    "hitLevels": "m",
    "damage": 17,
    "onBlock": "-16~-14",
    "onHit": "+14a",
    "onCounterHit": null,
    "states": "js8~26",
    "index": null
  },
  {
    "id": "Raven-uf+3+4,3+4",
    "parent": "Raven-uf+3+4",
    "name": "Spinning Chakram",
    "input": ",3+4",
    "startup": ",i20~24",
    "hitLevels": ",m",
    "damage": ",15",
    "onBlock": "-25~-21",
    "onHit": "+6a",
    "onCounterHit": null,
    "states": null,
    "index": 59
  },
  {
    "id": "Raven-uf+3+4,4",
    "parent": "Raven-uf+3+4",
    "name": null,
    "input": ",4",
    "startup": ",i21~22",
    "hitLevels": ",L",
    "damage": ",9",
    "onBlock": "-11~-10",
    "onHit": "+0~+1",
    "onCounterHit": null,
    "states": "cs1~41",
    "index": null
  },
  {
    "id": "Raven-uf+3+4,4,2",
    "parent": "Raven-uf+3+4,4",
    "name": "Chakram",
    "input": ",2",
    "startup": ",i21",
    "hitLevels": ",m",
    "damage": ",21",
    "onBlock": -13,
    "onHit": "+10a",
    "onCounterHit": null,
    "states": null,
    "index": 58
  },
  {
    "id": "Raven-uf+4",
    "parent": null,
    "name": null,
    "input": "uf+4",
    "startup": "i20~21",
    "hitLevels": "m",
    "damage": 14,
    "onBlock": "-9~-8",
    "onHit": "+22a (+12)",
    "onCounterHit": null,
    "states": "js8~27 fs28~30",
    "index": null
  },
  {
    "id": "Raven-uf+4,4",
    "parent": "Raven-uf+4",
    "name": "Stormbringer",
    "input": ",4",
    "startup": ",i16~19",
    "hitLevels": ",m",
    "damage": ",20",
    "onBlock": -15,
    "onHit": "+9g~12g",
    "onCounterHit": "+21a",
    "states": null,
    "index": 57
  },
  {
    "id": "Raven-uf,n,4",
    "parent": null,
    "name": "Delayed Rising Toe Kick",
    "input": "uf,n,4",
    "startup": "i23~25",
    "hitLevels": "m",
    "damage": 20,
    "onBlock": "-13~-11",
    "onHit": "+32a (+22)",
    "onCounterHit": null,
    "states": "js9~30 fs31~33",
    "index": 60
  },
  {
    "id": "Raven-ws1",
    "parent": null,
    "name": "Rising Uppercut",
    "input": "ws1",
    "startup": "i14~15",
    "hitLevels": "m",
    "damage": 14,
    "onBlock": "-14~-13",
    "onHit": "+35a (+25)",
    "onCounterHit": null,
    "states": null,
    "index": 70
  },
  {
    "id": "Raven-ws2",
    "parent": null,
    "name": "Jackknife Elbow",
    "input": "ws2",
    "startup": "i13~14",
    "hitLevels": "m",
    "damage": 17,
    "onBlock": "-8~-7",
    "onHit": "+8~+9",
    "onCounterHit": "+37a (+27)",
    "states": null,
    "index": 71
  },
  {
    "id": "Raven-ws3",
    "parent": null,
    "name": "Trident Kick",
    "input": "ws3",
    "startup": "i16~17",
    "hitLevels": "m",
    "damage": 18,
    "onBlock": "-8~-7",
    "onHit": "+0s",
    "onCounterHit": null,
    "states": null,
    "index": null
  },
  {
    "id": "Raven-ws3,2",
    "parent": "Raven-ws3",
    "name": "Trident Kick &gt; Phantom Halberd",
    "input": ",2",
    "startup": ",i19~20",
    "hitLevels": ",sm",
    "damage": ",20",
    "onBlock": -13,
    "onHit": "+65a (+49)",
    "onCounterHit": null,
    "states": null,
    "index": 72
  },
  {
    "id": "Raven-ws3+4",
    "parent": null,
    "name": "Spinning Middle Kick",
    "input": "ws3+4",
    "startup": "i16~18",
    "hitLevels": "m",
    "damage": 20,
    "onBlock": -9,
    "onHit": "+7~+9",
    "onCounterHit": null,
    "states": null,
    "index": 74
  },
  {
    "id": "Raven-ws3,H.2",
    "parent": "Raven-ws3",
    "name": "Trident Kick &gt; Phantom Halberd",
    "input": ",H.2",
    "startup": "i19~20, i39~41",
    "hitLevels": ",sm,sm",
    "damage": ",18,20",
    "onBlock": "-3~-1",
    "onHit": "+65a (+49)",
    "onCounterHit": null,
    "states": null,
    "index": null
  },
  {
    "id": "Raven-ws4",
    "parent": null,
    "name": "Shadow Snap Kick",
    "input": "ws4",
    "startup": "i11~12",
    "hitLevels": "m",
    "damage": 18,
    "onBlock": "-7~-6",
    "onHit": "+7~+8",
    "onCounterHit": 4,
    "states": null,
    "index": null
  }
]